Workbook

Sheet EJECUTIVO
C1: ALCALDÍA DE RIONEGRO · SECRETARÍA DE EDUCACIÓN | AB1: Etapa | AC1: Valor | AE1: Componente | AF1: Definitivo
C2: INFORME DE EJECUCIÓN PRESUPUESTAL — RESUMEN EJECUTIVO | AB2: Presupuesto Definitivo | AC2: =B7 | AE2: VIGENCIAS ANTERIORES | AF2: =B182
C3: Corte: 15 de septiembre de 2026 | AB3: Reservado CDP | AC3: =F7 | AE3: INFRAESTRUCTURA | AF3: =B177
C4: Fuente: Presupuesto de egreso a 15_09_2026.xls | Generado: 2026-09-18 | Rubros: 127 | AB4: Comprometido RP | AC4: =J7 | AE4: CALIDAD GRATUIDAD | AF4: =B160
AB5: Obligado OPS | AC5: =N7 | AE5: PRIMERA INFANCIA | AF5: =B173
B6: PRESUPUESTO DEFINITIVO | F6: RESERVADO CDP | J6: COMPROMETIDO RP | N6: OBLIGADO OPS | R6: PAGADO | AB6: Pagado | AC6: =R7 | AE6: CALIDAD MATRICULA | AF6: =B148
B7: =SEGUIMIENTO!H144 | F7: =SEGUIMIENTO!I144 | J7: =SEGUIMIENTO!J144 | N7: =SEGUIMIENTO!K144 | R7: =SEGUIMIENTO!L144 | AE7: SGP - PGN - PAE | AF7: =B162
AE8: RENDIMIENTOS O RECURSOS DEL BALANCE DE PRESTACION DEL SERVICIO | AF8: =B144
B9: Presupuesto disponible durante la vigencia. | F9: =IFERROR(F7/B7,0) | J9: =IFERROR(J7/B7,0) | N9: =IFERROR(N7/B7,0) | R9: =IFERROR(R7/B7,0) | AE9: PRESTACION DEL SERVICIO | AF9: =B46
F10: Cuenta con Certificado de Disponibilidad Presupuestal. | J10: Respaldado por Registro Presupuestal (contrato/obligación). | N10: Bien o servicio recibido; obligación exigible. | R10: Giro efectivo realizado a la fecha de corte. | AE10: RECURSOS PROPIOS O LIBRE INVERSION | AF10: =B128
A13: BRECHA DE EJECUCIÓN
B14: SIN RESERVAR | F14: SIN COMPROMETER | J14: SIN OBLIGAR
B15: =B7-F7 | F15: =B7-J7 | J15: =B7-N7
B17: =IFERROR(B15/B7,0) | F17: =IFERROR(F15/B7,0) | J17: =IFERROR(J15/B7,0)
B18: Presupuesto definitivo que aún no tiene CDP (Certificado de Disponibilidad Presupuestal). | F18: Presupuesto definitivo que aún no está respaldado por un RP (Registro Presupuestal). | J18: Presupuesto definitivo cuyo bien o servicio aún no ha sido recibido/certificado (OPS).
A38: LECTURA EJECUTIVA
A39: ="El "&TEXT(J9,"0.0%")&" del presupuesto definitivo está comprometido (RP)."
A40: ="El "&TEXT(R9,"0.0%")&" del presupuesto definitivo ha sido efectivamente pagado."
A41: ="La brecha sin comprometer, respecto al total, es de $"&TEXT(F15,"#,##0")&"."
A44: SEGUIMIENTO POR COMPONENTE
A45: Componente | B45: Ppto. Definitivo | C45: Reservado CDP | D45: Comprometido RP | E45: Obligado OPS | F45: Pagado | G45: % Pag | H45: Sin Reservar | I45: Sin Comprometer | J45: Sin Obligar | K45: % Comp
A46: PRESTACION DEL SERVICIO | B46: =SUMIF(SEGUIMIENTO!$A$2:$A$5000,"PRESTACION DEL SERVICIO",SEGUIMIENTO!$H$2:$H$5000) | C46: =SUMIF(SEGUIMIENTO!$A$2:$A$5000,"PRESTACION DEL SERVICIO",SEGUIMIENTO!$I$2:$I$5000) | D46: =SUMIF(SEGUIMIENTO!$A$2:$A$5000,"PRESTACION DEL SERVICIO",SEGUIMIENTO!$J$2:$J$5000) | E46: =SUMIF(SEGUIMIENTO!$A$2:$A$5000,"PRESTACION DEL SERVICIO",SEGUIMIENTO!$K$2:$K$5000) | F46: =SUMIF(SEGUIMIENTO!$A$2:$A$5000,"PRESTACION DEL SERVICIO",SEGUIMIENTO!$L$2:$L$5000) | G46: =IFERROR(F46/B46,0) | H46: =B46-C46 | I46: =B46-D46 | J46: =B46-E46 | K46: =IFERROR(D46/B46,0)
A47: Nomina Docente, Directivo y Administrativo | B47: =SUMIFS(SEGUIMIENTO!$H$2:$H$5000,SEGUIMIENTO!$A$2:$A$5000,"PRESTACION DEL SERVICIO",SEGUIMIENTO!$U$2:$U$5000,"Nomina Docente, Directivo y Administrativo") | C47: =SUMIFS(SEGUIMIENTO!$I$2:$I$5000,SEGUIMIENTO!$A$2:$A$5000,"PRESTACION DEL SERVICIO",SEGUIMIENTO!$U$2:$U$5000,"Nomina Docente, Directivo y Administrativo") | D47: =SUMIFS(SEGUIMIENTO!$J$2:$J$5000,SEGUIMIENTO!$A$2:$A$5000,"PRESTACION DEL SERVICIO",SEGUIMIENTO!$U$2:$U$5000,"Nomina Docente, Directivo y Administrativo") | E47: =SUMIFS(SEGUIMIENTO!$K$2:$K$5000,SEGUIMIENTO!$A$2:$A$5000,"PRESTACION DEL SERVICIO",SEGUIMIENTO!$U$2:$U$5000,"Nomina Docente, Directivo y Administrativo") | F47: =SUMIFS(SEGUIMIENTO!$L$2:$L$5000,SEGUIMIENTO!$A$2:$A$5000,"PRESTACION DEL SERVICIO",SEGUIMIENTO!$U$2:$U$5000,"Nomina Docente, Directivo y Administrativo") | G47: =IFERROR(F47/B47,0) | H47: =B47-C47 | I47: =B47-D47 | J47: =B47-E47 | K47: =IFERROR(D47/B47,0)
A48: Sueldos Directivos Docentes Sin Situación de Fondos | B48: =SEGUIMIENTO!H2 | C48: =SEGUIMIENTO!I2 | D48: =SEGUIMIENTO!J2 | E48: =SEGUIMIENTO!K2 | F48: =SEGUIMIENTO!L2 | G48: =IFERROR(F48/B48,0) | H48: =B48-C48 | I48: =B48-D48 | J48: =B48-E48 | K48: =IFERROR(D48/B48,0)
A49: Sueldo Directivos Docentes Con Situación de Fondos | B49: =SEGUIMIENTO!H3 | C49: =SEGUIMIENTO!I3 | D49: =SEGUIMIENTO!J3 | E49: =SEGUIMIENTO!K3 | F49: =SEGUIMIENTO!L3 | G49: =IFERROR(F49/B49,0) | H49: =B49-C49 | I49: =B49-D49 | J49: =B49-E49 | K49: =IFERROR(D49/B49,0)
A50: Sueldo Administrativo | B50: =SEGUIMIENTO!H4 | C50: =SEGUIMIENTO!I4 | D50: =SEGUIMIENTO!J4 | E50: =SEGUIMIENTO!K4 | F50: =SEGUIMIENTO!L4 | G50: =IFERROR(F50/B50,0) | H50: =B50-C50 | I50: =B50-D50 | J50: =B50-E50 | K50: =IFERROR(D50/B50,0)
A51: Sueldo Docentes Con Situación de Fondos | B51: =SEGUIMIENTO!H5 | C51: =SEGUIMIENTO!I5 | D51: =SEGUIMIENTO!J5 | E51: =SEGUIMIENTO!K5 | F51: =SEGUIMIENTO!L5 | G51: =IFERROR(F51/B51,0) | H51: =B51-C51 | I51: =B51-D51 | J51: =B51-E51 | K51: =IFERROR(D51/B51,0)
A52: Sueldo Docentes Sin Situación de Fondos | B52: =SEGUIMIENTO!H6 | C52: =SEGUIMIENTO!I6 | D52: =SEGUIMIENTO!J6 | E52: =SEGUIMIENTO!K6 | F52: =SEGUIMIENTO!L6 | G52: =IFERROR(F52/B52,0) | H52: =B52-C52 | I52: =B52-D52 | J52: =B52-E52 | K52: =IFERROR(D52/B52,0)
A53: Horas Extra y días festivos Sin Situación de Fondos Directivos Docentes | B53: =SEGUIMIENTO!H7 | C53: =SEGUIMIENTO!I7 | D53: =SEGUIMIENTO!J7 | E53: =SEGUIMIENTO!K7 | F53: =SEGUIMIENTO!L7 | G53: =IFERROR(F53/B53,0) | H53: =B53-C53 | I53: =B53-D53 | J53: =B53-E53 | K53: =IFERROR(D53/B53,0)
A54: Horas Extras y días festivos Con Situación de Fondos Directivos Docentes | B54: =SEGUIMIENTO!H8 | C54: =SEGUIMIENTO!I8 | D54: =SEGUIMIENTO!J8 | E54: =SEGUIMIENTO!K8 | F54: =SEGUIMIENTO!L8 | G54: =IFERROR(F54/B54,0) | H54: =B54-C54 | I54: =B54-D54 | J54: =B54-E54 | K54: =IFERROR(D54/B54,0)
A55: Horas Extras y días festivos Administrativos | B55: =SEGUIMIENTO!H9 | C55: =SEGUIMIENTO!I9 | D55: =SEGUIMIENTO!J9 | E55: =SEGUIMIENTO!K9 | F55: =SEGUIMIENTO!L9 | G55: =IFERROR(F55/B55,0) | H55: =B55-C55 | I55: =B55-D55 | J55: =B55-E55 | K55: =IFERROR(D55/B55,0)
A56: Horas Extras y días festivos Sin Situación de Fondos Docentes | B56: =SEGUIMIENTO!H10 | C56: =SEGUIMIENTO!I10 | D56: =SEGUIMIENTO!J10 | E56: =SEGUIMIENTO!K10 | F56: =SEGUIMIENTO!L10 | G56: =IFERROR(F56/B56,0) | H56: =B56-C56 | I56: =B56-D56 | J56: =B56-E56 | K56: =IFERROR(D56/B56,0)
A57: Horas Extras y días festivos Con Situación de Fondos Docentes | B57: =SEGUIMIENTO!H11 | C57: =SEGUIMIENTO!I11 | D57: =SEGUIMIENTO!J11 | E57: =SEGUIMIENTO!K11 | F57: =SEGUIMIENTO!L11 | G57: =IFERROR(F57/B57,0) | H57: =B57-C57 | I57: =B57-D57 | J57: =B57-E57 | K57: =IFERROR(D57/B57,0)
A58: Subsidio o prima de alimentación Administrativo | B58: =SEGUIMIENTO!H12 | C58: =SEGUIMIENTO!I12 | D58: =SEGUIMIENTO!J12 | E58: =SEGUIMIENTO!K12 | F58: =SEGUIMIENTO!L12 | G58: =IFERROR(F58/B58,0) | H58: =B58-C58 | I58: =B58-D58 | J58: =B58-E58 | K58: =IFERROR(D58/B58,0)
A59: Subsidio o prima de alimentación Docentes | B59: =SEGUIMIENTO!H13 | C59: =SEGUIMIENTO!I13 | D59: =SEGUIMIENTO!J13 | E59: =SEGUIMIENTO!K13 | F59: =SEGUIMIENTO!L13 | G59: =IFERROR(F59/B59,0) | H59: =B59-C59 | I59: =B59-D59 | J59: =B59-E59 | K59: =IFERROR(D59/B59,0)
... A117: RF SGP- Prestación del Servicio educación | B117: =SEGUIMIENTO!H71 | C117: =SEGUIMIENTO!I71 | D117: =SEGUIMIENTO!J71 | E117: =SEGUIMIENTO!K71 | F117: =SEGUIMIENTO!L71 | G117: =IFERROR(F117/B117,0) | H117: =B117-C117 | I117: =B117-D117 | J117: =B117-E117 | K117: =IFERROR(D117/B117,0)
A118: Otros Gastos Administrativos | B118: =SUMIFS(SEGUIMIENTO!$H$2:$H$5000,SEGUIMIENTO!$A$2:$A$5000,"PRESTACION DEL SERVICIO",SEGUIMIENTO!$U$2:$U$5000,"Otros Gastos Administrativos") | C118: =SUMIFS(SEGUIMIENTO!$I$2:$I$5000,SEGUIMIENTO!$A$2:$A$5000,"PRESTACION DEL SERVICIO",SEGUIMIENTO!$U$2:$U$5000,"Otros Gastos Administrativos") | D118: =SUMIFS(SEGUIMIENTO!$J$2:$J$5000,SEGUIMIENTO!$A$2:$A$5000,"PRESTACION DEL SERVICIO",SEGUIMIENTO!$U$2:$U$5000,"Otros Gastos Administrativos") | E118: =SUMIFS(SEGUIMIENTO!$K$2:$K$5000,SEGUIMIENTO!$A$2:$A$5000,"PRESTACION DEL SERVICIO",SEGUIMIENTO!$U$2:$U$5000,"Otros Gastos Administrativos") | F118: =SUMIFS(SEGUIMIENTO!$L$2:$L$5000,SEGUIMIENTO!$A$2:$A$5000,"PRESTACION DEL SERVICIO",SEGUIMIENTO!$U$2:$U$5000,"Otros Gastos Administrativos") | G118: =IFERROR(F118/B118,0) | H118: =B118-C118 | I118: =B118-D118 | J118: =B118-E118 | K118: =IFERROR(D118/B118,0)
A119: Fortalecimiento de estrategias para la permanencia escolar otros administrativos | B119: =SEGUIMIENTO!H73 | C119: =SEGUIMIENTO!I73 | D119: =SEGUIMIENTO!J73 | E119: =SEGUIMIENTO!K73 | F119: =SEGUIMIENTO!L73 | G119: =IFERROR(F119/B119,0) | H119: =B119-C119 | I119: =B119-D119 | J119: =B119-E119 | K119: =IFERROR(D119/B119,0)
A120: SVC Aseo | B120: =SUMIFS(SEGUIMIENTO!$H$2:$H$5000,SEGUIMIENTO!$A$2:$A$5000,"PRESTACION DEL SERVICIO",SEGUIMIENTO!$U$2:$U$5000,"SVC Aseo") | C120: =SUMIFS(SEGUIMIENTO!$I$2:$I$5000,SEGUIMIENTO!$A$2:$A$5000,"PRESTACION DEL SERVICIO",SEGUIMIENTO!$U$2:$U$5000,"SVC Aseo") | D120: =SUMIFS(SEGUIMIENTO!$J$2:$J$5000,SEGUIMIENTO!$A$2:$A$5000,"PRESTACION DEL SERVICIO",SEGUIMIENTO!$U$2:$U$5000,"SVC Aseo") | E120: =SUMIFS(SEGUIMIENTO!$K$2:$K$5000,SEGUIMIENTO!$A$2:$A$5000,"PRESTACION DEL SERVICIO",SEGUIMIENTO!$U$2:$U$5000,"SVC Aseo") | F120: =SUMIFS(SEGUIMIENTO!$L$2:$L$5000,SEGUIMIENTO!$A$2:$A$5000,"PRESTACION DEL SERVICIO",SEGUIMIENTO!$U$2:$U$5000,"SVC Aseo") | G120: =IFERROR(F120/B120,0) | H120: =B120-C120 | I120: =B120-D120 | J120: =B120-E120 | K120: =IFERROR(D120/B120,0)
A121: Fortalecimiento de estrategias para la permanencia escolar svc aseo | B121: =SEGUIMIENTO!H75 | C121: =SEGUIMIENTO!I75 | D121: =SEGUIMIENTO!J75 | E121: =SEGUIMIENTO!K75 | F121: =SEGUIMIENTO!L75 | G121: =IFERROR(F121/B121,0) | H121: =B121-C121 | I121: =B121-D121 | J121: =B121-E121 | K121: =IFERROR(D121/B121,0)
A122: SVC Vigilancia | B122: =SUMIFS(SEGUIMIENTO!$H$2:$H$5000,SEGUIMIENTO!$A$2:$A$5000,"PRESTACION DEL SERVICIO",SEGUIMIENTO!$U$2:$U$5000,"SVC Vigilancia") | C122: =SUMIFS(SEGUIMIENTO!$I$2:$I$5000,SEGUIMIENTO!$A$2:$A$5000,"PRESTACION DEL SERVICIO",SEGUIMIENTO!$U$2:$U$5000,"SVC Vigilancia") | D122: =SUMIFS(SEGUIMIENTO!$J$2:$J$5000,SEGUIMIENTO!$A$2:$A$5000,"PRESTACION DEL SERVICIO",SEGUIMIENTO!$U$2:$U$5000,"SVC Vigilancia") | E122: =SUMIFS(SEGUIMIENTO!$K$2:$K$5000,SEGUIMIENTO!$A$2:$A$5000,"PRESTACION DEL SERVICIO",SEGUIMIENTO!$U$2:$U$5000,"SVC Vigilancia") | F122: =SUMIFS(SEGUIMIENTO!$L$2:$L$5000,SEGUIMIENTO!$A$2:$A$5000,"PRESTACION DEL SERVICIO",SEGUIMIENTO!$U$2:$U$5000,"SVC Vigilancia") | G122: =IFERROR(F122/B122,0) | H122: =B122-C122 | I122: =B122-D122 | J122: =B122-E122 | K122: =IFERROR(D122/B122,0)
A123: Fortalecimiento de estrategias para la permanencia escolar svc vigilancia | B123: =SEGUIMIENTO!H77 | C123: =SEGUIMIENTO!I77 | D123: =SEGUIMIENTO!J77 | E123: =SEGUIMIENTO!K77 | F123: =SEGUIMIENTO!L77 | G123: =IFERROR(F123/B123,0) | H123: =B123-C123 | I123: =B123-D123 | J123: =B123-E123 | K123: =IFERROR(D123/B123,0)
A124: Conectividad | B124: =SUMIFS(SEGUIMIENTO!$H$2:$H$5000,SEGUIMIENTO!$A$2:$A$5000,"PRESTACION DEL SERVICIO",SEGUIMIENTO!$U$2:$U$5000,"Conectividad") | C124: =SUMIFS(SEGUIMIENTO!$I$2:$I$5000,SEGUIMIENTO!$A$2:$A$5000,"PRESTACION DEL SERVICIO",SEGUIMIENTO!$U$2:$U$5000,"Conectividad") | D124: =SUMIFS(SEGUIMIENTO!$J$2:$J$5000,SEGUIMIENTO!$A$2:$A$5000,"PRESTACION DEL SERVICIO",SEGUIMIENTO!$U$2:$U$5000,"Conectividad") | E124: =SUMIFS(SEGUIMIENTO!$K$2:$K$5000,SEGUIMIENTO!$A$2:$A$5000,"PRESTACION DEL SERVICIO",SEGUIMIENTO!$U$2:$U$5000,"Conectividad") | F124: =SUMIFS(SEGUIMIENTO!$L$2:$L$5000,SEGUIMIENTO!$A$2:$A$5000,"PRESTACION DEL SERVICIO",SEGUIMIENTO!$U$2:$U$5000,"Conectividad") | G124: =IFERROR(F124/B124,0) | H124: =B124-C124 | I124: =B124-D124 | J124: =B124-E124 | K124: =IFERROR(D124/B124,0)
A125: Conectividad | B125: =SEGUIMIENTO!H79 | C125: =SEGUIMIENTO!I79 | D125: =SEGUIMIENTO!J79 | E125: =SEGUIMIENTO!K79 | F125: =SEGUIMIENTO!L79 | G125: =IFERROR(F125/B125,0) | H125: =B125-C125 | I125: =B125-D125 | J125: =B125-E125 | K125: =IFERROR(D125/B125,0)
A126: Necesidades Educativas Especiales | B126: =SUMIFS(SEGUIMIENTO!$H$2:$H$5000,SEGUIMIENTO!$A$2:$A$5000,"PRESTACION DEL SERVICIO",SEGUIMIENTO!$U$2:$U$5000,"Necesidades Educativas Especiales") | C126: =SUMIFS(SEGUIMIENTO!$I$2:$I$5000,SEGUIMIENTO!$A$2:$A$5000,"PRESTACION DEL SERVICIO",SEGUIMIENTO!$U$2:$U$5000,"Necesidades Educativas Especiales") | D126: =SUMIFS(SEGUIMIENTO!$J$2:$J$5000,SEGUIMIENTO!$A$2:$A$5000,"PRESTACION DEL SERVICIO",SEGUIMIENTO!$U$2:$U$5000,"Necesidades Educativas Especiales") | E126: =SUMIFS(SEGUIMIENTO!$K$2:$K$5000,SEGUIMIENTO!$A$2:$A$5000,"PRESTACION DEL SERVICIO",SEGUIMIENTO!$U$2:$U$5000,"Necesidades Educativas Especiales") | F126: =SUMIFS(SEGUIMIENTO!$L$2:$L$5000,SEGUIMIENTO!$A$2:$A$5000,"PRESTACION DEL SERVICIO",SEGUIMIENTO!$U$2:$U$5000,"Necesidades Educativas Especiales") | G126: =IFERROR(F126/B126,0) | H126: =B126-C126 | I126: =B126-D126 | J126: =B126-E126 | K126: =IFERROR(D126/B126,0)
A127: Atención a población con necesidades especiales o discapacidades | B127: =SEGUIMIENTO!H81 | C127: =SEGUIMIENTO!I81 | D127: =SEGUIMIENTO!J81 | E127: =SEGUIMIENTO!K81 | F127: =SEGUIMIENTO!L81 | G127: =IFERROR(F127/B127,0) | H127: =B127-C127 | I127: =B127-D127 | J127: =B127-E127 | K127: =IFERROR(D127/B127,0)
A128: RECURSOS PROPIOS O LIBRE INVERSION | B128: =SUMIF(SEGUIMIENTO!$A$2:$A$5000,"RECURSOS PROPIOS O LIBRE INVERSION",SEGUIMIENTO!$H$2:$H$5000) | C128: =SUMIF(SEGUIMIENTO!$A$2:$A$5000,"RECURSOS PROPIOS O LIBRE INVERSION",SEGUIMIENTO!$I$2:$I$5000) | D128: =SUMIF(SEGUIMIENTO!$A$2:$A$5000,"RECURSOS PROPIOS O LIBRE INVERSION",SEGUIMIENTO!$J$2:$J$5000) | E128: =SUMIF(SEGUIMIENTO!$A$2:$A$5000,"RECURSOS PROPIOS O LIBRE INVERSION",SEGUIMIENTO!$K$2:$K$5000) | F128: =SUMIF(SEGUIMIENTO!$A$2:$A$5000,"RECURSOS PROPIOS O LIBRE INVERSION",SEGUIMIENTO!$L$2:$L$5000) | G128: =IFERROR(F128/B128,0) | H128: =B128-C128 | I128: =B128-D128 | J128: =B128-E128 | K128: =IFERROR(D128/B128,0)
A129: 020103 Ciudadela Educativa Etapa 1 | B129: =SEGUIMIENTO!H84 | C129: =SEGUIMIENTO!I84 | D129: =SEGUIMIENTO!J84 | E129: =SEGUIMIENTO!K84 | F129: =SEGUIMIENTO!L84 | G129: =IFERROR(F129/B129,0) | H129: =B129-C129 | I129: =B129-D129 | J129: =B129-E129 | K129: =IFERROR(D129/B129,0)
A130: 020102 Formulación e implementación del plan Decenal de Educación | B130: =SEGUIMIENTO!H85 | C130: =SEGUIMIENTO!I85 | D130: =SEGUIMIENTO!J85 | E130: =SEGUIMIENTO!K85 | F130: =SEGUIMIENTO!L85 | G130: =IFERROR(F130/B130,0) | H130: =B130-C130 | I130: =B130-D130 | J130: =B130-E130 | K130: =IFERROR(D130/B130,0)
A131: 020105 Desarrollo del programa de bienestar para docentes y directivos docentes | B131: =SEGUIMIENTO!H86 | C131: =SEGUIMIENTO!I86 | D131: =SEGUIMIENTO!J86 | E131: =SEGUIMIENTO!K86 | F131: =SEGUIMIENTO!L86 | G131: =IFERROR(F131/B131,0) | H131: =B131-C131 | I131: =B131-D131 | J131: =B131-E131 | K131: =IFERROR(D131/B131,0)
A132: 020106 Mejoramiento de la cobertura Educativa PAE | B132: =SEGUIMIENTO!H87 | C132: =SEGUIMIENTO!I87 | D132: =SEGUIMIENTO!J87 | E132: =SEGUIMIENTO!K87 | F132: =SEGUIMIENTO!L87 | G132: =IFERROR(F132/B132,0) | H132: =B132-C132 | I132: =B132-D132 | J132: =B132-E132 | K132: =IFERROR(D132/B132,0)
A133: 020106 Mejoramiento de la cobertura Educativa Paquetes PAE | B133: =SEGUIMIENTO!H88 | C133: =SEGUIMIENTO!I88 | D133: =SEGUIMIENTO!J88 | E133: =SEGUIMIENTO!K88 | F133: =SEGUIMIENTO!L88 | G133: =IFERROR(F133/B133,0) | H133: =B133-C133 | I133: =B133-D133 | J133: =B133-E133 | K133: =IFERROR(D133/B133,0)
A134: 020101 VF Fortalecimiento de la pertinencia y la calidad educativa | B134: =SEGUIMIENTO!H89 | C134: =SEGUIMIENTO!I89 | D134: =SEGUIMIENTO!J89 | E134: =SEGUIMIENTO!K89 | F134: =SEGUIMIENTO!L89 | G134: =IFERROR(F134/B134,0) | H134: =B134-C134 | I134: =B134-D134 | J134: =B134-E134 | K134: =IFERROR(D134/B134,0)
A135: 020101 Fortalecimiento de la pertinencia y la calidad educativa | B135: =SEGUIMIENTO!H90 | C135: =SEGUIMIENTO!I90 | D135: =SEGUIMIENTO!J90 | E135: =SEGUIMIENTO!K90 | F135: =SEGUIMIENTO!L90 | G135: =IFERROR(F135/B135,0) | H135: =B135-C135 | I135: =B135-D135 | J135: =B135-E135 | K135: =IFERROR(D135/B135,0)
A136: 020107 Fortalecimiento del programa de Bilinguismo | B136: =SEGUIMIENTO!H91 | C136: =SEGUIMIENTO!I91 | D136: =SEGUIMIENTO!J91 | E136: =SEGUIMIENTO!K91 | F136: =SEGUIMIENTO!L91 | G136: =IFERROR(F136/B136,0) | H136: =B136-C136 | I136: =B136-D136 | J136: =B136-E136 | K136: =IFERROR(D136/B136,0)
A137: 020104 Fortalecimiento de la Educación técnica, tecnológica y superior | B137: =SEGUIMIENTO!H92 | C137: =SEGUIMIENTO!I92 | D137: =SEGUIMIENTO!J92 | E137: =SEGUIMIENTO!K92 | F137: =SEGUIMIENTO!L92 | G137: =IFERROR(F137/B137,0) | H137: =B137-C137 | I137: =B137-D137 | J137: =B137-E137 | K137: =IFERROR(D137/B137,0)
A138: 020108 Fortalecimiento del Bienestar Institucional | B138: =SEGUIMIENTO!H93 | C138: =SEGUIMIENTO!I93 | D138: =SEGUIMIENTO!J93 | E138: =SEGUIMIENTO!K93 | F138: =SEGUIMIENTO!L93 | G138: =IFERROR(F138/B138,0) | H138: =B138-C138 | I138: =B138-D138 | J138: =B138-E138 | K138: =IFERROR(D138/B138,0)
A139: 020101 Fortalecimiento de la pertinencia y la calidad educativa | B139: =SEGUIMIENTO!H94 | C139: =SEGUIMIENTO!I94 | D139: =SEGUIMIENTO!J94 | E139: =SEGUIMIENTO!K94 | F139: =SEGUIMIENTO!L94 | G139: =IFERROR(F139/B139,0) | H139: =B139-C139 | I139: =B139-D139 | J139: =B139-E139 | K139: =IFERROR(D139/B139,0)
A140: 020106 Mejoramiento de la cobertura Educativa Equipo | B140: =SEGUIMIENTO!H95 | C140: =SEGUIMIENTO!I95 | D140: =SEGUIMIENTO!J95 | E140: =SEGUIMIENTO!K95 | F140: =SEGUIMIENTO!L95 | G140: =IFERROR(F140/B140,0) | H140: =B140-C140 | I140: =B140-D140 | J140: =B140-E140 | K140: =IFERROR(D140/B140,0)
... A143: 020103 Fortalecimiento de Infraestructura y Ambientes de Aprendizaje para el bienestar | B143: =SEGUIMIENTO!H98 | C143: =SEGUIMIENTO!I98 | D143: =SEGUIMIENTO!J98 | E143: =SEGUIMIENTO!K98 | F143: =SEGUIMIENTO!L98 | G143: =IFERROR(F143/B143,0) | H143: =B143-C143 | I143: =B143-D143 | J143: =B143-E143 | K143: =IFERROR(D143/B143,0)
A144: RENDIMIENTOS O RECURSOS DEL BALANCE DE PRESTACION DEL SERVICIO | B144: =SUMIF(SEGUIMIENTO!$A$2:$A$5000,"RENDIMIENTOS O RECURSOS DEL BALANCE DE PRESTACION DEL SERVICIO",SEGUIMIENTO!$H$2:$H$5000) | C144: =SUMIF(SEGUIMIENTO!$A$2:$A$5000,"RENDIMIENTOS O RECURSOS DEL BALANCE DE PRESTACION DEL SERVICIO",SEGUIMIENTO!$I$2:$I$5000) | D144: =SUMIF(SEGUIMIENTO!$A$2:$A$5000,"RENDIMIENTOS O RECURSOS DEL BALANCE DE PRESTACION DEL SERVICIO",SEGUIMIENTO!$J$2:$J$5000) | E144: =SUMIF(SEGUIMIENTO!$A$2:$A$5000,"RENDIMIENTOS O RECURSOS DEL BALANCE DE PRESTACION DEL SERVICIO",SEGUIMIENTO!$K$2:$K$5000) | F144: =SUMIF(SEGUIMIENTO!$A$2:$A$5000,"RENDIMIENTOS O RECURSOS DEL BALANCE DE PRESTACION DEL SERVICIO",SEGUIMIENTO!$L$2:$L$5000) | G144: =IFERROR(F144/B144,0) | H144: =B144-C144 | I144: =B144-D144 | J144: =B144-E144 | K144: =IFERROR(D144/B144,0)
A145: Sueldo Docentes Con Situación de Fondos | B145: =SEGUIMIENTO!H100 | C145: =SEGUIMIENTO!I100 | D145: =SEGUIMIENTO!J100 | E145: =SEGUIMIENTO!K100 | F145: =SEGUIMIENTO!L100 | G145: =IFERROR(F145/B145,0) | H145: =B145-C145 | I145: =B145-D145 | J145: =B145-E145 | K145: =IFERROR(D145/B145,0)
A146: Sueldo Docentes Con Situación de Fondos | B146: =SEGUIMIENTO!H101 | C146: =SEGUIMIENTO!I101 | D146: =SEGUIMIENTO!J101 | E146: =SEGUIMIENTO!K101 | F146: =SEGUIMIENTO!L101 | G146: =IFERROR(F146/B146,0) | H146: =B146-C146 | I146: =B146-D146 | J146: =B146-E146 | K146: =IFERROR(D146/B146,0)
A147: Aportes Patronales previsión social SSF Vig-2024 | B147: =SEGUIMIENTO!H102 | C147: =SEGUIMIENTO!I102 | D147: =SEGUIMIENTO!J102 | E147: =SEGUIMIENTO!K102 | F147: =SEGUIMIENTO!L102 | G147: =IFERROR(F147/B147,0) | H147: =B147-C147 | I147: =B147-D147 | J147: =B147-E147 | K147: =IFERROR(D147/B147,0)
A148: CALIDAD MATRICULA | B148: =SUMIF(SEGUIMIENTO!$A$2:$A$5000,"CALIDAD MATRICULA",SEGUIMIENTO!$H$2:$H$5000) | C148: =SUMIF(SEGUIMIENTO!$A$2:$A$5000,"CALIDAD MATRICULA",SEGUIMIENTO!$I$2:$I$5000) | D148: =SUMIF(SEGUIMIENTO!$A$2:$A$5000,"CALIDAD MATRICULA",SEGUIMIENTO!$J$2:$J$5000) | E148: =SUMIF(SEGUIMIENTO!$A$2:$A$5000,"CALIDAD MATRICULA",SEGUIMIENTO!$K$2:$K$5000) | F148: =SUMIF(SEGUIMIENTO!$A$2:$A$5000,"CALIDAD MATRICULA",SEGUIMIENTO!$L$2:$L$5000) | G148: =IFERROR(F148/B148,0) | H148: =B148-C148 | I148: =B148-D148 | J148: =B148-E148 | K148: =IFERROR(D148/B148,0)
A149: Dotación Institucional de Material y medios pedagógicos | B149: =SEGUIMIENTO!H104 | C149: =SEGUIMIENTO!I104 | D149: =SEGUIMIENTO!J104 | E149: =SEGUIMIENTO!K104 | F149: =SEGUIMIENTO!L104 | G149: =IFERROR(F149/B149,0) | H149: =B149-C149 | I149: =B149-D149 | J149: =B149-E149 | K149: =IFERROR(D149/B149,0)
A150: Mantenimiento de Infraestructura Educativa | B150: =SEGUIMIENTO!H105 | C150: =SEGUIMIENTO!I105 | D150: =SEGUIMIENTO!J105 | E150: =SEGUIMIENTO!K105 | F150: =SEGUIMIENTO!L105 | G150: =IFERROR(F150/B150,0) | H150: =B150-C150 | I150: =B150-D150 | J150: =B150-E150 | K150: =IFERROR(D150/B150,0)
A151: 020103 Mantenimiento de Infraestructura Educativa | B151: =SEGUIMIENTO!H106 | C151: =SEGUIMIENTO!I106 | D151: =SEGUIMIENTO!J106 | E151: =SEGUIMIENTO!K106 | F151: =SEGUIMIENTO!L106 | G151: =IFERROR(F151/B151,0) | H151: =B151-C151 | I151: =B151-D151 | J151: =B151-E151 | K151: =IFERROR(D151/B151,0)
A152: 020103 Mantenimiento de Infraestructura Educativa | B152: =SEGUIMIENTO!H107 | C152: =SEGUIMIENTO!I107 | D152: =SEGUIMIENTO!J107 | E152: =SEGUIMIENTO!K107 | F152: =SEGUIMIENTO!L107 | G152: =IFERROR(F152/B152,0) | H152: =B152-C152 | I152: =B152-D152 | J152: =B152-E152 | K152: =IFERROR(D152/B152,0)
A153: 020103 Mantenimiento de Infraestructura Educativa | B153: =SEGUIMIENTO!H108 | C153: =SEGUIMIENTO!I108 | D153: =SEGUIMIENTO!J108 | E153: =SEGUIMIENTO!K108 | F153: =SEGUIMIENTO!L108 | G153: =IFERROR(F153/B153,0) | H153: =B153-C153 | I153: =B153-D153 | J153: =B153-E153 | K153: =IFERROR(D153/B153,0)
A154: Fortalecimiento de estrategias para la permanencia escolar | B154: =SEGUIMIENTO!H109 | C154: =SEGUIMIENTO!I109 | D154: =SEGUIMIENTO!J109 | E154: =SEGUIMIENTO!K109 | F154: =SEGUIMIENTO!L109 | G154: =IFERROR(F154/B154,0) | H154: =B154-C154 | I154: =B154-D154 | J154: =B154-E154 | K154: =IFERROR(D154/B154,0)
A155: Servicios públicos instituciones educativas | B155: =SEGUIMIENTO!H110 | C155: =SEGUIMIENTO!I110 | D155: =SEGUIMIENTO!J110 | E155: =SEGUIMIENTO!K110 | F155: =SEGUIMIENTO!L110 | G155: =IFERROR(F155/B155,0) | H155: =B155-C155 | I155: =B155-D155 | J155: =B155-E155 | K155: =IFERROR(D155/B155,0)
A156: Capacitacion de docentes y directivos docentes | B156: =SEGUIMIENTO!H111 | C156: =SEGUIMIENTO!I111 | D156: =SEGUIMIENTO!J111 | E156: =SEGUIMIENTO!K111 | F156: =SEGUIMIENTO!L111 | G156: =IFERROR(F156/B156,0) | H156: =B156-C156 | I156: =B156-D156 | J156: =B156-E156 | K156: =IFERROR(D156/B156,0)
A157: RB SGP-EDUCACION-CALIDAD POR MATRICULA OFICIAL | B157: =SEGUIMIENTO!H112 | C157: =SEGUIMIENTO!I112 | D157: =SEGUIMIENTO!J112 | E157: =SEGUIMIENTO!K112 | F157: =SEGUIMIENTO!L112 | G157: =IFERROR(F157/B157,0) | H157: =B157-C157 | I157: =B157-D157 | J157: =B157-E157 | K157: =IFERROR(D157/B157,0)
A158: RB RF SGP - EDUCACION-CALIDAD POR MATRICULA OFICIAL | B158: =SEGUIMIENTO!H113 | C158: =SEGUIMIENTO!I113 | D158: =SEGUIMIENTO!J113 | E158: =SEGUIMIENTO!K113 | F158: =SEGUIMIENTO!L113 | G158: =IFERROR(F158/B158,0) | H158: =B158-C158 | I158: =B158-D158 | J158: =B158-E158 | K158: =IFERROR(D158/B158,0)
A159: RF SGP- Calidad Matricula | B159: =SEGUIMIENTO!H114 | C159: =SEGUIMIENTO!I114 | D159: =SEGUIMIENTO!J114 | E159: =SEGUIMIENTO!K114 | F159: =SEGUIMIENTO!L114 | G159: =IFERROR(F159/B159,0) | H159: =B159-C159 | I159: =B159-D159 | J159: =B159-E159 | K159: =IFERROR(D159/B159,0)
A160: CALIDAD GRATUIDAD | B160: =SUMIF(SEGUIMIENTO!$A$2:$A$5000,"CALIDAD GRATUIDAD",SEGUIMIENTO!$H$2:$H$5000) | C160: =SUMIF(SEGUIMIENTO!$A$2:$A$5000,"CALIDAD GRATUIDAD",SEGUIMIENTO!$I$2:$I$5000) | D160: =SUMIF(SEGUIMIENTO!$A$2:$A$5000,"CALIDAD GRATUIDAD",SEGUIMIENTO!$J$2:$J$5000) | E160: =SUMIF(SEGUIMIENTO!$A$2:$A$5000,"CALIDAD GRATUIDAD",SEGUIMIENTO!$K$2:$K$5000) | F160: =SUMIF(SEGUIMIENTO!$A$2:$A$5000,"CALIDAD GRATUIDAD",SEGUIMIENTO!$L$2:$L$5000) | G160: =IFERROR(F160/B160,0) | H160: =B160-C160 | I160: =B160-D160 | J160: =B160-E160 | K160: =IFERROR(D160/B160,0)
A161: Fondos de Servicios Educativos de las Instituciones de Preescolar, básica y Media | B161: =SEGUIMIENTO!H116 | C161: =SEGUIMIENTO!I116 | D161: =SEGUIMIENTO!J116 | E161: =SEGUIMIENTO!K116 | F161: =SEGUIMIENTO!L116 | G161: =IFERROR(F161/B161,0) | H161: =B161-C161 | I161: =B161-D161 | J161: =B161-E161 | K161: =IFERROR(D161/B161,0)
A162: SGP - PGN - PAE | B162: =SUMIF(SEGUIMIENTO!$A$2:$A$5000,"SGP - PGN - PAE",SEGUIMIENTO!$H$2:$H$5000) | C162: =SUMIF(SEGUIMIENTO!$A$2:$A$5000,"SGP - PGN - PAE",SEGUIMIENTO!$I$2:$I$5000) | D162: =SUMIF(SEGUIMIENTO!$A$2:$A$5000,"SGP - PGN - PAE",SEGUIMIENTO!$J$2:$J$5000) | E162: =SUMIF(SEGUIMIENTO!$A$2:$A$5000,"SGP - PGN - PAE",SEGUIMIENTO!$K$2:$K$5000) | F162: =SUMIF(SEGUIMIENTO!$A$2:$A$5000,"SGP - PGN - PAE",SEGUIMIENTO!$L$2:$L$5000) | G162: =IFERROR(F162/B162,0) | H162: =B162-C162 | I162: =B162-D162 | J162: =B162-E162 | K162: =IFERROR(D162/B162,0)
A163: ECB RES 295 NOV 05 2021 MINEDUCACIÓN PROGRAMA DE ALIMENTACIÓN ESCOLAR PAE | B163: =SEGUIMIENTO!H118 | C163: =SEGUIMIENTO!I118 | D163: =SEGUIMIENTO!J118 | E163: =SEGUIMIENTO!K118 | F163: =SEGUIMIENTO!L118 | G163: =IFERROR(F163/B163,0) | H163: =B163-C163 | I163: =B163-D163 | J163: =B163-E163 | K163: =IFERROR(D163/B163,0)
A164: 020106 Mejoramiento de la cobertura Educativa PAE | B164: =SEGUIMIENTO!H119 | C164: =SEGUIMIENTO!I119 | D164: =SEGUIMIENTO!J119 | E164: =SEGUIMIENTO!K119 | F164: =SEGUIMIENTO!L119 | G164: =IFERROR(F164/B164,0) | H164: =B164-C164 | I164: =B164-D164 | J164: =B164-E164 | K164: =IFERROR(D164/B164,0)
A165: 020106 Mejoramiento de la cobertura Educativa PAE | B165: =SEGUIMIENTO!H120 | C165: =SEGUIMIENTO!I120 | D165: =SEGUIMIENTO!J120 | E165: =SEGUIMIENTO!K120 | F165: =SEGUIMIENTO!L120 | G165: =IFERROR(F165/B165,0) | H165: =B165-C165 | I165: =B165-D165 | J165: =B165-E165 | K165: =IFERROR(D165/B165,0)
A166: 020106 Mejoramiento de la cobertura Educativa PAE | B166: =SEGUIMIENTO!H121 | C166: =SEGUIMIENTO!I121 | D166: =SEGUIMIENTO!J121 | E166: =SEGUIMIENTO!K121 | F166: =SEGUIMIENTO!L121 | G166: =IFERROR(F166/B166,0) | H166: =B166-C166 | I166: =B166-D166 | J166: =B166-E166 | K166: =IFERROR(D166/B166,0)
A167: RB RF SGP - ASIGNACION ESPECIAL-PROGRAMAS DE ALIMENTACION ESCOLAR | B167: =SEGUIMIENTO!H122 | C167: =SEGUIMIENTO!I122 | D167: =SEGUIMIENTO!J122 | E167: =SEGUIMIENTO!K122 | F167: =SEGUIMIENTO!L122 | G167: =IFERROR(F167/B167,0) | H167: =B167-C167 | I167: =B167-D167 | J167: =B167-E167 | K167: =IFERROR(D167/B167,0)
A168: ECB RES 295 NOV 05 2021 MINEDUCACIÓN PROGRAMA DE ALIMENTACIÓN ESCOLAR PAE | B168: =SEGUIMIENTO!H123 | C168: =SEGUIMIENTO!I123 | D168: =SEGUIMIENTO!J123 | E168: =SEGUIMIENTO!K123 | F168: =SEGUIMIENTO!L123 | G168: =IFERROR(F168/B168,0) | H168: =B168-C168 | I168: =B168-D168 | J168: =B168-E168 | K168: =IFERROR(D168/B168,0)
A169: RES 388 DEL 17 NOV DE 2023 PROGR ALIMENTAC ESCOLAR PAE | B169: =SEGUIMIENTO!H124 | C169: =SEGUIMIENTO!I124 | D169: =SEGUIMIENTO!J124 | E169: =SEGUIMIENTO!K124 | F169: =SEGUIMIENTO!L124 | G169: =IFERROR(F169/B169,0) | H169: =B169-C169 | I169: =B169-D169 | J169: =B169-E169 | K169: =IFERROR(D169/B169,0)
A170: RF Recursos SGP Alimentación Escolar | B170: =SEGUIMIENTO!H125 | C170: =SEGUIMIENTO!I125 | D170: =SEGUIMIENTO!J125 | E170: =SEGUIMIENTO!K125 | F170: =SEGUIMIENTO!L125 | G170: =IFERROR(F170/B170,0) | H170: =B170-C170 | I170: =B170-D170 | J170: =B170-E170 | K170: =IFERROR(D170/B170,0)
A171: 020106 RF Mejoramiento de la cobertura Educativa PAE | B171: =SEGUIMIENTO!H126 | C171: =SEGUIMIENTO!I126 | D171: =SEGUIMIENTO!J126 | E171: =SEGUIMIENTO!K126 | F171: =SEGUIMIENTO!L126 | G171: =IFERROR(F171/B171,0) | H171: =B171-C171 | I171: =B171-D171 | J171: =B171-E171 | K171: =IFERROR(D171/B171,0)
A172: 020106 RF LI Mejoramiento de la cobertura Educativa PAE | B172: =SEGUIMIENTO!H127 | C172: =SEGUIMIENTO!I127 | D172: =SEGUIMIENTO!J127 | E172: =SEGUIMIENTO!K127 | F172: =SEGUIMIENTO!L127 | G172: =IFERROR(F172/B172,0) | H172: =B172-C172 | I172: =B172-D172 | J172: =B172-E172 | K172: =IFERROR(D172/B172,0)
A173: PRIMERA INFANCIA | B173: =SUMIF(SEGUIMIENTO!$A$2:$A$5000,"PRIMERA INFANCIA",SEGUIMIENTO!$H$2:$H$5000) | C173: =SUMIF(SEGUIMIENTO!$A$2:$A$5000,"PRIMERA INFANCIA",SEGUIMIENTO!$I$2:$I$5000) | D173: =SUMIF(SEGUIMIENTO!$A$2:$A$5000,"PRIMERA INFANCIA",SEGUIMIENTO!$J$2:$J$5000) | E173: =SUMIF(SEGUIMIENTO!$A$2:$A$5000,"PRIMERA INFANCIA",SEGUIMIENTO!$K$2:$K$5000) | F173: =SUMIF(SEGUIMIENTO!$A$2:$A$5000,"PRIMERA INFANCIA",SEGUIMIENTO!$L$2:$L$5000) | G173: =IFERROR(F173/B173,0) | H173: =B173-C173 | I173: =B173-D173 | J173: =B173-E173 | K173: =IFERROR(D173/B173,0)
A174: 010101 Acompañamiento en la atención a la primera infancia | B174: =SEGUIMIENTO!H129 | C174: =SEGUIMIENTO!I129 | D174: =SEGUIMIENTO!J129 | E174: =SEGUIMIENTO!K129 | F174: =SEGUIMIENTO!L129 | G174: =IFERROR(F174/B174,0) | H174: =B174-C174 | I174: =B174-D174 | J174: =B174-E174 | K174: =IFERROR(D174/B174,0)
A175: RB RF SGP - ASIGNACION-ATENCION INTEGRAL DE LA PRIMERA INFANCIA | B175: =SEGUIMIENTO!H130 | C175: =SEGUIMIENTO!I130 | D175: =SEGUIMIENTO!J130 | E175: =SEGUIMIENTO!K130 | F175: =SEGUIMIENTO!L130 | G175: =IFERROR(F175/B175,0) | H175: =B175-C175 | I175: =B175-D175 | J175: =B175-E175 | K175: =IFERROR(D175/B175,0)
A176: RB SGP-ASIGNACION-ATENCION INTEGRAL DE LA PRIMERA INFANCIA | B176: =SEGUIMIENTO!H131 | C176: =SEGUIMIENTO!I131 | D176: =SEGUIMIENTO!J131 | E176: =SEGUIMIENTO!K131 | F176: =SEGUIMIENTO!L131 | G176: =IFERROR(F176/B176,0) | H176: =B176-C176 | I176: =B176-D176 | J176: =B176-E176 | K176: =IFERROR(D176/B176,0)
A177: INFRAESTRUCTURA | B177: =SUMIF(SEGUIMIENTO!$A$2:$A$5000,"INFRAESTRUCTURA",SEGUIMIENTO!$H$2:$H$5000) | C177: =SUMIF(SEGUIMIENTO!$A$2:$A$5000,"INFRAESTRUCTURA",SEGUIMIENTO!$I$2:$I$5000) | D177: =SUMIF(SEGUIMIENTO!$A$2:$A$5000,"INFRAESTRUCTURA",SEGUIMIENTO!$J$2:$J$5000) | E177: =SUMIF(SEGUIMIENTO!$A$2:$A$5000,"INFRAESTRUCTURA",SEGUIMIENTO!$K$2:$K$5000) | F177: =SUMIF(SEGUIMIENTO!$A$2:$A$5000,"INFRAESTRUCTURA",SEGUIMIENTO!$L$2:$L$5000) | G177: =IFERROR(F177/B177,0) | H177: =B177-C177 | I177: =B177-D177 | J177: =B177-E177 | K177: =IFERROR(D177/B177,0)
A178: RF CI 1878 NOV 10 VF 2022 MINIST INTERIOR FONSECON SACUDETE AL PARQUE TIPO 2 | B178: =SEGUIMIENTO!H133 | C178: =SEGUIMIENTO!I133 | D178: =SEGUIMIENTO!J133 | E178: =SEGUIMIENTO!K133 | F178: =SEGUIMIENTO!L133 | G178: =IFERROR(F178/B178,0) | H178: =B178-C178 | I178: =B178-D178 | J178: =B178-E178 | K178: =IFERROR(D178/B178,0)
A179: 020103 CI 1878 NOV 10 VF 2022 MINIST INTERIOR FONSECON SACUDETE AL PARQUE TIPO 2 | B179: =SEGUIMIENTO!H134 | C179: =SEGUIMIENTO!I134 | D179: =SEGUIMIENTO!J134 | E179: =SEGUIMIENTO!K134 | F179: =SEGUIMIENTO!L134 | G179: =IFERROR(F179/B179,0) | H179: =B179-C179 | I179: =B179-D179 | J179: =B179-E179 | K179: =IFERROR(D179/B179,0)
A180: ECB RF CI 1878 NOV 10 VF 2022 MINIST INTERIOR FONSECON SACUDETE AL PARQUE TIPO 2 | B180: =SEGUIMIENTO!H135 | C180: =SEGUIMIENTO!I135 | D180: =SEGUIMIENTO!J135 | E180: =SEGUIMIENTO!K135 | F180: =SEGUIMIENTO!L135 | G180: =IFERROR(F180/B180,0) | H180: =B180-C180 | I180: =B180-D180 | J180: =B180-E180 | K180: =IFERROR(D180/B180,0)
A181: DC CI 1878 NOV 10 VF 2022 MINIST INTERIOR FONSECON SACUDETE AL PARQUE TIPO 2 | B181: =SEGUIMIENTO!H136 | C181: =SEGUIMIENTO!I136 | D181: =SEGUIMIENTO!J136 | E181: =SEGUIMIENTO!K136 | F181: =SEGUIMIENTO!L136 | G181: =IFERROR(F181/B181,0) | H181: =B181-C181 | I181: =B181-D181 | J181: =B181-E181 | K181: =IFERROR(D181/B181,0)
A182: VIGENCIAS ANTERIORES | B182: =SUMIF(SEGUIMIENTO!$A$2:$A$5000,"VIGENCIAS ANTERIORES",SEGUIMIENTO!$H$2:$H$5000) | C182: =SUMIF(SEGUIMIENTO!$A$2:$A$5000,"VIGENCIAS ANTERIORES",SEGUIMIENTO!$I$2:$I$5000) | D182: =SUMIF(SEGUIMIENTO!$A$2:$A$5000,"VIGENCIAS ANTERIORES",SEGUIMIENTO!$J$2:$J$5000) | E182: =SUMIF(SEGUIMIENTO!$A$2:$A$5000,"VIGENCIAS ANTERIORES",SEGUIMIENTO!$K$2:$K$5000) | F182: =SUMIF(SEGUIMIENTO!$A$2:$A$5000,"VIGENCIAS ANTERIORES",SEGUIMIENTO!$L$2:$L$5000) | G182: =IFERROR(F182/B182,0) | H182: =B182-C182 | I182: =B182-D182 | J182: =B182-E182 | K182: =IFERROR(D182/B182,0)
A183: ECB RF COFINANCIACIÓN DEL MEN | B183: =SEGUIMIENTO!H138 | C183: =SEGUIMIENTO!I138 | D183: =SEGUIMIENTO!J138 | E183: =SEGUIMIENTO!K138 | F183: =SEGUIMIENTO!L138 | G183: =IFERROR(F183/B183,0) | H183: =B183-C183 | I183: =B183-D183 | J183: =B183-E183 | K183: =IFERROR(D183/B183,0)
...

Sheet SEGUIMIENTO
A1: Componente | B1: Naturaleza | C1: Codigo rubro | D1: cons_ppt | E1: Proyecto / Rubro | F1: Fondo | G1: Fuente | H1: Definitivo | I1: Reservado CDP | J1: Comprometido RP | K1: Obligado OPS | L1: Pagado | M1: Sin reservar | N1: Sin comprometer | O1: Sin obligar | P1: % Comp | Q1: % Pag | R1: Contratos | S1: Responsable | T1: Observacion | U1: Subgrupo
A2: PRESTACION DEL SERVICIO | B2: Nomina y aportes | C2: 02.01.2.3.1.01.01.001.01.001 | D2: 4865 | E2: Sueldos Directivos Docentes Sin Situación de Fondos | F2: 1.2.4.1.01 | G2: SGP-EDUCACION-PRESTACION DE SERVICIOS | H2: 371740660 | I2: 276440189 | J2: 276440189 | K2: 276440189 | L2: 276440189 | M2: =H2-I2 | N2: =I2-J2 | O2: =J2-K2 | P2: =IFERROR(J2/H2,"") | Q2: =IFERROR(L2/H2,"") | R2: Sin contratos | U2: Nomina Docente, Directivo y Administrativo
A3: PRESTACION DEL SERVICIO | B3: Nomina y aportes | C3: 02.01.2.3.1.01.01.001.01.002 | D3: 4866 | E3: Sueldo Directivos Docentes Con Situación de Fondos | F3: 1.2.4.1.01 | G3: SGP-EDUCACION-PRESTACION DE SERVICIOS | H3: 4127246171 | I3: 2946272302 | J3: 2944410737 | K3: 2944410737 | L3: 2944410737 | M3: =H3-I3 | N3: =I3-J3 | O3: =J3-K3 | P3: =IFERROR(J3/H3,"") | Q3: =IFERROR(L3/H3,"") | R3: Sin contratos | U3: Nomina Docente, Directivo y Administrativo
A4: PRESTACION DEL SERVICIO | B4: Nomina y aportes | C4: 02.01.2.3.1.01.01.001.01.003 | D4: 4867 | E4: Sueldo Administrativo | F4: 1.2.4.1.01 | G4: SGP-EDUCACION-PRESTACION DE SERVICIOS | H4: 449933960 | I4: 273314317 | J4: 273314317 | K4: 273314317 | L4: 273314317 | M4: =H4-I4 | N4: =I4-J4 | O4: =J4-K4 | P4: =IFERROR(J4/H4,"") | Q4: =IFERROR(L4/H4,"") | R4: Sin contratos | U4: Nomina Docente, Directivo y Administrativo
A5: PRESTACION DEL SERVICIO | B5: Nomina y aportes | C5: 02.01.2.3.1.01.01.001.01.004 | D5: 4868 | E5: Sueldo Docentes Con Situación de Fondos | F5: 1.2.4.1.01 | G5: SGP-EDUCACION-PRESTACION DE SERVICIOS | H5: 50187458743 | I5: 35442189914 | J5: 35442189914 | K5: 35442189914 | L5: 35442189914 | M5: =H5-I5 | N5: =I5-J5 | O5: =J5-K5 | P5: =IFERROR(J5/H5,"") | Q5: =IFERROR(L5/H5,"") | R5: Sin contratos | U5: Nomina Docente, Directivo y Administrativo
A6: PRESTACION DEL SERVICIO | B6: Nomina y aportes | C6: 02.01.2.3.1.01.01.001.01.005 | D6: 4869 | E6: Sueldo Docentes Sin Situación de Fondos | F6: 1.2.4.1.01 | G6: SGP-EDUCACION-PRESTACION DE SERVICIOS | H6: 4214618702 | I6: 3203544986 | J6: 3203544986 | K6: 3203544986 | L6: 3203544986 | M6: =H6-I6 | N6: =I6-J6 | O6: =J6-K6 | P6: =IFERROR(J6/H6,"") | Q6: =IFERROR(L6/H6,"") | R6: Sin contratos | U6: Nomina Docente, Directivo y Administrativo
A7: PRESTACION DEL SERVICIO | B7: Nomina y aportes | C7: 02.01.2.3.1.01.01.001.02.001 | D7: 4871 | E7: Horas Extra y días festivos Sin Situación de Fondos Directivos Docentes | F7: 1.2.4.1.01 | G7: SGP-EDUCACION-PRESTACION DE SERVICIOS | H7: 3973131 | I7: 3973131 | J7: 1578062 | K7: 1578062 | L7: 1578062 | M7: =H7-I7 | N7: =I7-J7 | O7: =J7-K7 | P7: =IFERROR(J7/H7,"") | Q7: =IFERROR(L7/H7,"") | R7: Sin contratos | U7: Nomina Docente, Directivo y Administrativo
A8: PRESTACION DEL SERVICIO | B8: Nomina y aportes | C8: 02.01.2.3.1.01.01.001.02.002 | D8: 4872 | E8: Horas Extras y días festivos Con Situación de Fondos Directivos Docentes | F8: 1.2.4.1.01 | G8: SGP-EDUCACION-PRESTACION DE SERVICIOS | H8: 29467958 | I8: 29467958 | J8: 18147722 | K8: 18147722 | L8: 18147722 | M8: =H8-I8 | N8: =I8-J8 | O8: =J8-K8 | P8: =IFERROR(J8/H8,"") | Q8: =IFERROR(L8/H8,"") | R8: Sin contratos | U8: Nomina Docente, Directivo y Administrativo
A9: PRESTACION DEL SERVICIO | B9: Nomina y aportes | C9: 02.01.2.3.1.01.01.001.02.003 | D9: 4873 | E9: Horas Extras y días festivos Administrativos | F9: 1.2.4.1.01 | G9: SGP-EDUCACION-PRESTACION DE SERVICIOS | H9: 73685952 | I9: 73685952 | J9: 20712030 | K9: 20712030 | L9: 20712030 | M9: =H9-I9 | N9: =I9-J9 | O9: =J9-K9 | P9: =IFERROR(J9/H9,"") | Q9: =IFERROR(L9/H9,"") | R9: Sin contratos | U9: Nomina Docente, Directivo y Administrativo
A10: PRESTACION DEL SERVICIO | B10: Nomina y aportes | C10: 02.01.2.3.1.01.01.001.02.004 | D10: 4874 | E10: Horas Extras y días festivos Sin Situación de Fondos Docentes | F10: 1.2.4.1.01 | G10: SGP-EDUCACION-PRESTACION DE SERVICIOS | H10: 60342374 | I10: 60342374 | J10: 42069697 | K10: 42069697 | L10: 42069697 | M10: =H10-I10 | N10: =I10-J10 | O10: =J10-K10 | P10: =IFERROR(J10/H10,"") | Q10: =IFERROR(L10/H10,"") | R10: Sin contratos | U10: Nomina Docente, Directivo y Administrativo
A11: PRESTACION DEL SERVICIO | B11: Nomina y aportes | C11: 02.01.2.3.1.01.01.001.02.005 | D11: 4875 | E11: Horas Extras y días festivos Con Situación de Fondos Docentes | F11: 1.2.4.1.01 | G11: SGP-EDUCACION-PRESTACION DE SERVICIOS | H11: 693937310 | I11: 693937310 | J11: 486380834 | K11: 486380834 | L11: 486380834 | M11: =H11-I11 | N11: =I11-J11 | O11: =J11-K11 | P11: =IFERROR(J11/H11,"") | Q11: =IFERROR(L11/H11,"") | R11: Sin contratos | U11: Nomina Docente, Directivo y Administrativo
A12: PRESTACION DEL SERVICIO | B12: Nomina y aportes | C12: 02.01.2.3.1.01.01.001.04.001 | D12: 4877 | E12: Subsidio o prima de alimentación Administrativo | F12: 1.2.4.1.01 | G12: SGP-EDUCACION-PRESTACION DE SERVICIOS | H12: 10652394 | I12: 5141074 | J12: 5141074 | K12: 5141074 | L12: 5141074 | M12: =H12-I12 | N12: =I12-J12 | O12: =J12-K12 | P12: =IFERROR(J12/H12,"") | Q12: =IFERROR(L12/H12,"") | R12: Sin contratos | U12: Nomina Docente, Directivo y Administrativo
A13: PRESTACION DEL SERVICIO | B13: Nomina y aportes | C13: 02.01.2.3.1.01.01.001.04.002 | D13: 4878 | E13: Subsidio o prima de alimentación Docentes | F13: 1.2.4.1.01 | G13: SGP-EDUCACION-PRESTACION DE SERVICIOS | H13: 29669138 | I13: 10020479 | J13: 10020479 | K13: 10020479 | L13: 10020479 | M13: =H13-I13 | N13: =I13-J13 | O13: =J13-K13 | P13: =IFERROR(J13/H13,"") | Q13: =IFERROR(L13/H13,"") | R13: Sin contratos | U13: Nomina Docente, Directivo y Administrativo
... A71: PRESTACION DEL SERVICIO | B71: Inversion / proyectos | C71: 02.01.2.3.2.02.02.009.110 | D71: 5827 | E71: RF SGP- Prestación del Servicio educación | F71: 1.3.2.2.01 | G71: R.F. SGP - EDUCACION-PRESTACION DE SERVICIO EDUCATIVO | H71: 0 | I71: 0 | J71: 0 | K71: 0 | L71: 0 | M71: =H71-I71 | N71: =I71-J71 | O71: =J71-K71 | P71: =IFERROR(J71/H71,"") | Q71: =IFERROR(L71/H71,"") | R71: Sin contratos | U71: Nomina Docente, Directivo y Administrativo
A72: SUBTOTAL Nomina Docente, Directivo y Administrativo | H72: =SUM(H2:H71) | I72: =SUM(I2:I71) | J72: =SUM(J2:J71) | K72: =SUM(K2:K71) | L72: =SUM(L2:L71) | M72: =H72-I72 | N72: =I72-J72 | O72: =J72-K72 | P72: =IFERROR(J72/H72,0) | Q72: =IFERROR(L72/H72,0)
A73: PRESTACION DEL SERVICIO | B73: Inversion / proyectos | C73: 02.01.2.3.2.02.02.009.028 | D73: 4965 | E73: Fortalecimiento de estrategias para la permanencia escolar otros administrativos | F73: 1.2.4.1.01 | G73: SGP-EDUCACION-PRESTACION DE SERVICIOS | H73: 785200240 | I73: 610842311 | J73: 480257600 | K73: 315000000 | L73: 315000000 | M73: =H73-I73 | N73: =I73-J73 | O73: =J73-K73 | P73: =IFERROR(J73/H73,"") | Q73: =IFERROR(L73/H73,"") | R73: Sin contratos | U73: Otros Gastos Administrativos
A74: SUBTOTAL Otros Gastos Administrativos | H74: =SUM(H73:H73) | I74: =SUM(I73:I73) | J74: =SUM(J73:J73) | K74: =SUM(K73:K73) | L74: =SUM(L73:L73) | M74: =H74-I74 | N74: =I74-J74 | O74: =J74-K74 | P74: =IFERROR(J74/H74,0) | Q74: =IFERROR(L74/H74,0)
A75: PRESTACION DEL SERVICIO | B75: Inversion / proyectos | C75: 02.01.2.3.2.02.02.009.026 | D75: 4963 | E75: Fortalecimiento de estrategias para la permanencia escolar svc aseo | F75: 1.2.4.1.01 | G75: SGP-EDUCACION-PRESTACION DE SERVICIOS | H75: 759871200 | I75: 759871200 | J75: 759871200 | K75: 0 | L75: 0 | M75: =H75-I75 | N75: =I75-J75 | O75: =J75-K75 | P75: =IFERROR(J75/H75,"") | Q75: =IFERROR(L75/H75,"") | R75: 1 contrato | $759,871,200 comprometido | U75: SVC Aseo
A76: SUBTOTAL SVC Aseo | H76: =SUM(H75:H75) | I76: =SUM(I75:I75) | J76: =SUM(J75:J75) | K76: =SUM(K75:K75) | L76: =SUM(L75:L75) | M76: =H76-I76 | N76: =I76-J76 | O76: =J76-K76 | P76: =IFERROR(J76/H76,0) | Q76: =IFERROR(L76/H76,0)
A77: PRESTACION DEL SERVICIO | B77: Inversion / proyectos | C77: 02.01.2.3.2.02.02.009.027 | D77: 4964 | E77: Fortalecimiento de estrategias para la permanencia escolar svc vigilancia | F77: 1.2.4.1.01 | G77: SGP-EDUCACION-PRESTACION DE SERVICIOS | H77: 759871200 | I77: 759871200 | J77: 759871200 | K77: 214080729 | L77: 214080729 | M77: =H77-I77 | N77: =I77-J77 | O77: =J77-K77 | P77: =IFERROR(J77/H77,"") | Q77: =IFERROR(L77/H77,"") | R77: Sin contratos | U77: SVC Vigilancia
A78: SUBTOTAL SVC Vigilancia | H78: =SUM(H77:H77) | I78: =SUM(I77:I77) | J78: =SUM(J77:J77) | K78: =SUM(K77:K77) | L78: =SUM(L77:L77) | M78: =H78-I78 | N78: =I78-J78 | O78: =J78-K78 | P78: =IFERROR(J78/H78,0) | Q78: =IFERROR(L78/H78,0)
A79: PRESTACION DEL SERVICIO | B79: Inversion / proyectos | C79: 02.01.2.3.2.02.02.009.029 | D79: 4966 | E79: Conectividad | F79: 1.2.4.1.01 | G79: SGP-EDUCACION-PRESTACION DE SERVICIOS | H79: 417066544 | I79: 0 | J79: 0 | K79: 0 | L79: 0 | M79: =H79-I79 | N79: =I79-J79 | O79: =J79-K79 | P79: =IFERROR(J79/H79,"") | Q79: =IFERROR(L79/H79,"") | R79: Sin contratos | U79: Conectividad
A80: SUBTOTAL Conectividad | H80: =SUM(H79:H79) | I80: =SUM(I79:I79) | J80: =SUM(J79:J79) | K80: =SUM(K79:K79) | L80: =SUM(L79:L79) | M80: =H80-I80 | N80: =I80-J80 | O80: =J80-K80 | P80: =IFERROR(J80/H80,0) | Q80: =IFERROR(L80/H80,0)
A81: PRESTACION DEL SERVICIO | B81: Inversion / proyectos | C81: 02.01.2.3.2.02.02.009.030 | D81: 4967 | E81: Atención a población con necesidades especiales o discapacidades | F81: 1.2.4.1.01 | G81: SGP-EDUCACION-PRESTACION DE SERVICIOS | H81: 379869229 | I81: 379869229 | J81: 379869229 | K81: 379869229 | L81: 379869229 | M81: =H81-I81 | N81: =I81-J81 | O81: =J81-K81 | P81: =IFERROR(J81/H81,"") | Q81: =IFERROR(L81/H81,"") | R81: 1 contrato | $379,869,229 comprometido | U81: Necesidades Educativas Especiales
A82: SUBTOTAL Necesidades Educativas Especiales | H82: =SUM(H81:H81) | I82: =SUM(I81:I81) | J82: =SUM(J81:J81) | K82: =SUM(K81:K81) | L82: =SUM(L81:L81) | M82: =H82-I82 | N82: =I82-J82 | O82: =J82-K82 | P82: =IFERROR(J82/H82,0) | Q82: =IFERROR(L82/H82,0)
A83: SUBTOTAL PRESTACION DEL SERVICIO | H83: =SUM(H72,H74,H76,H78,H80,H82) | I83: =SUM(I72,I74,I76,I78,I80,I82) | J83: =SUM(J72,J74,J76,J78,J80,J82) | K83: =SUM(K72,K74,K76,K78,K80,K82) | L83: =SUM(L72,L74,L76,L78,L80,L82) | M83: =H83-I83 | N83: =I83-J83 | O83: =J83-K83 | P83: =IFERROR(J83/H83,0) | Q83: =IFERROR(L83/H83,0)
A84: RECURSOS PROPIOS O LIBRE INVERSION | B84: Inversion / proyectos | C84: 02.01.2.3.2.02.02.005.009 | D84: 5869 | E84: 020103 Ciudadela Educativa Etapa 1 | F84: 1.3.1.1.05.04 | G84: RECURSOS DE CREDITO INTERNO | H84: 42000000000 | I84: 34257295709 | J84: 34257295709 | K84: 15399242347 | L84: 15399242347 | M84: =H84-I84 | N84: =I84-J84 | O84: =J84-K84 | P84: =IFERROR(J84/H84,"") | Q84: =IFERROR(L84/H84,"") | R84: Sin contratos | U84: RECURSOS PROPIOS O LIBRE INVERSION
A85: RECURSOS PROPIOS O LIBRE INVERSION | B85: Inversion / proyectos | C85: 02.01.2.3.2.02.02.009.031 | D85: 4976 | E85: 020102 Formulación e implementación del plan Decenal de Educación | F85: 1.2.1.0.00 | G85: INGRESOS CORRIENTES DE LIBRE DESTINACION | H85: 0 | I85: 0 | J85: 0 | K85: 0 | L85: 0 | M85: =H85-I85 | N85: =I85-J85 | O85: =J85-K85 | P85: =IFERROR(J85/H85,"") | Q85: =IFERROR(L85/H85,"") | R85: Sin contratos | U85: RECURSOS PROPIOS O LIBRE INVERSION
A86: RECURSOS PROPIOS O LIBRE INVERSION | B86: Inversion / proyectos | C86: 02.01.2.3.2.02.02.009.038 | D86: 4981 | E86: 020105 Desarrollo del programa de bienestar para docentes y directivos docentes | F86: 1.2.1.0.00 | G86: INGRESOS CORRIENTES DE LIBRE DESTINACION | H86: 261614015 | I86: 261614015 | J86: 18195388 | K86: 18195388 | L86: 18195388 | M86: =H86-I86 | N86: =I86-J86 | O86: =J86-K86 | P86: =IFERROR(J86/H86,"") | Q86: =IFERROR(L86/H86,"") | R86: Sin contratos | U86: RECURSOS PROPIOS O LIBRE INVERSION
A87: RECURSOS PROPIOS O LIBRE INVERSION | B87: Inversion / proyectos | C87: 02.01.2.3.2.02.02.009.039 | D87: 4985 | E87: 020106 Mejoramiento de la cobertura Educativa PAE | F87: 1.2.1.0.00 | G87: INGRESOS CORRIENTES DE LIBRE DESTINACION | H87: 27344058931 | I87: 27344058931 | J87: 27217166386 | K87: 7985014808 | L87: 7548707923 | M87: =H87-I87 | N87: =I87-J87 | O87: =J87-K87 | P87: =IFERROR(J87/H87,"") | Q87: =IFERROR(L87/H87,"") | R87: 6 contratos | $27,217,166,386 comprometido | U87: RECURSOS PROPIOS O LIBRE INVERSION
A88: RECURSOS PROPIOS O LIBRE INVERSION | B88: Inversion / proyectos | C88: 02.01.2.3.2.02.02.009.040 | D88: 4986 | E88: 020106 Mejoramiento de la cobertura Educativa Paquetes PAE | F88: 1.2.1.0.00 | G88: INGRESOS CORRIENTES DE LIBRE DESTINACION | H88: 7721361064 | I88: 7338263218 | J88: 7320703987 | K88: 3411171557 | L88: 1133544243 | M88: =H88-I88 | N88: =I88-J88 | O88: =J88-K88 | P88: =IFERROR(J88/H88,"") | Q88: =IFERROR(L88/H88,"") | R88: 1 contrato | $3,794,269,403 comprometido | U88: RECURSOS PROPIOS O LIBRE INVERSION
A89: RECURSOS PROPIOS O LIBRE INVERSION | B89: Inversion / proyectos | C89: 02.01.2.3.2.02.02.009.042 | D89: 4972 | E89: 020101 VF Fortalecimiento de la pertinencia y la calidad educativa | F89: 1.2.1.0.00 | G89: INGRESOS CORRIENTES DE LIBRE DESTINACION | H89: 3.0865868e+09 | I89: 2902424207 | J89: 2902424207 | K89: 2902424207 | L89: 2902424207 | M89: =H89-I89 | N89: =I89-J89 | O89: =J89-K89 | P89: =IFERROR(J89/H89,"") | Q89: =IFERROR(L89/H89,"") | R89: 2 contratos | $2,902,424,207 comprometido | U89: RECURSOS PROPIOS O LIBRE INVERSION
A90: RECURSOS PROPIOS O LIBRE INVERSION | B90: Inversion / proyectos | C90: 02.01.2.3.2.02.02.009.043 | D90: 4973 | E90: 020101 Fortalecimiento de la pertinencia y la calidad educativa | F90: 1.2.1.0.00 | G90: INGRESOS CORRIENTES DE LIBRE DESTINACION | H90: 109270604 | I90: 45506000 | J90: 20306000 | K90: 11213763 | L90: 11213763 | M90: =H90-I90 | N90: =I90-J90 | O90: =J90-K90 | P90: =IFERROR(J90/H90,"") | Q90: =IFERROR(L90/H90,"") | R90: 1 contrato | $20,306,000 comprometido | U90: RECURSOS PROPIOS O LIBRE INVERSION
A91: RECURSOS PROPIOS O LIBRE INVERSION | B91: Inversion / proyectos | C91: 02.01.2.3.2.02.02.009.044 | D91: 4995 | E91: 020107 Fortalecimiento del programa de Bilinguismo | F91: 1.2.1.0.00 | G91: INGRESOS CORRIENTES DE LIBRE DESTINACION | H91: 2125253816 | I91: 1530633596 | J91: 1530633596 | K91: 0 | L91: 0 | M91: =H91-I91 | N91: =I91-J91 | O91: =J91-K91 | P91: =IFERROR(J91/H91,"") | Q91: =IFERROR(L91/H91,"") | R91: 1 contrato | $941,332,078 comprometido | U91: RECURSOS PROPIOS O LIBRE INVERSION
A92: RECURSOS PROPIOS O LIBRE INVERSION | B92: Inversion / proyectos | C92: 02.01.2.3.2.02.02.009.045 | D92: 4979 | E92: 020104 Fortalecimiento de la Educación técnica, tecnológica y superior | F92: 1.2.1.0.00 | G92: INGRESOS CORRIENTES DE LIBRE DESTINACION | H92: 750999040 | I92: 750999040 | J92: 463568362 | K92: 463568362 | L92: 201282900 | M92: =H92-I92 | N92: =I92-J92 | O92: =J92-K92 | P92: =IFERROR(J92/H92,"") | Q92: =IFERROR(L92/H92,"") | R92: Sin contratos | U92: RECURSOS PROPIOS O LIBRE INVERSION
A93: RECURSOS PROPIOS O LIBRE INVERSION | B93: Inversion / proyectos | C93: 02.01.2.3.2.02.02.009.046 | D93: 4996 | E93: 020108 Fortalecimiento del Bienestar Institucional | F93: 1.2.1.0.00 | G93: INGRESOS CORRIENTES DE LIBRE DESTINACION | H93: 8346289732 | I93: 7941535948 | J93: 7663802309 | K93: 798613653 | L93: 386530709 | M93: =H93-I93 | N93: =I93-J93 | O93: =J93-K93 | P93: =IFERROR(J93/H93,"") | Q93: =IFERROR(L93/H93,"") | R93: 3 contratos | $4,222,234,277 comprometido | U93: RECURSOS PROPIOS O LIBRE INVERSION
A94: RECURSOS PROPIOS O LIBRE INVERSION | B94: Inversion / proyectos | C94: 02.01.2.3.2.02.02.009.047 | D94: 4974 | E94: 020101 Fortalecimiento de la pertinencia y la calidad educativa | F94: 1.2.1.0.00 | G94: INGRESOS CORRIENTES DE LIBRE DESTINACION | H94: 1250429381 | I94: 1250429381 | J94: 0 | K94: 0 | L94: 0 | M94: =H94-I94 | N94: =I94-J94 | O94: =J94-K94 | P94: =IFERROR(J94/H94,"") | Q94: =IFERROR(L94/H94,"") | R94: Sin contratos | U94: RECURSOS PROPIOS O LIBRE INVERSION
A95: RECURSOS PROPIOS O LIBRE INVERSION | B95: Inversion / proyectos | C95: 02.01.2.3.2.02.02.009.048 | D95: 4987 | E95: 020106 Mejoramiento de la cobertura Educativa Equipo | F95: 1.2.1.0.00 | G95: INGRESOS CORRIENTES DE LIBRE DESTINACION | H95: 0 | I95: 0 | J95: 0 | K95: 0 | L95: 0 | M95: =H95-I95 | N95: =I95-J95 | O95: =J95-K95 | P95: =IFERROR(J95/H95,"") | Q95: =IFERROR(L95/H95,"") | R95: Sin contratos | U95: RECURSOS PROPIOS O LIBRE INVERSION
... A98: RECURSOS PROPIOS O LIBRE INVERSION | B98: Inversion / proyectos | C98: 02.01.2.3.2.02.02.009.085 | D98: 4978 | E98: 020103 Fortalecimiento de Infraestructura y Ambientes de Aprendizaje para el bienestar | F98: 1.2.1.0.00 | G98: INGRESOS CORRIENTES DE LIBRE DESTINACION | H98: 0 | I98: 0 | J98: 0 | K98: 0 | L98: 0 | M98: =H98-I98 | N98: =I98-J98 | O98: =J98-K98 | P98: =IFERROR(J98/H98,"") | Q98: =IFERROR(L98/H98,"") | R98: Sin contratos | U98: RECURSOS PROPIOS O LIBRE INVERSION
A99: SUBTOTAL RECURSOS PROPIOS O LIBRE INVERSION | H99: =SUM(H84:H98) | I99: =SUM(I84:I98) | J99: =SUM(J84:J98) | K99: =SUM(K84:K98) | L99: =SUM(L84:L98) | M99: =H99-I99 | N99: =I99-J99 | O99: =J99-K99 | P99: =IFERROR(J99/H99,0) | Q99: =IFERROR(L99/H99,0)
A100: RENDIMIENTOS O RECURSOS DEL BALANCE DE PRESTACION DEL SERVICIO | B100: Nomina y aportes | C100: 02.01.2.3.1.01.01.001.01.006 | D100: 6808 | E100: Sueldo Docentes Con Situación de Fondos | F100: 1.3.3.6.01 | G100: R.B. SGP-EDUCACION-PRESTACIÃ¿N DE SERVICIO EDUCATIVO | H100: 1.127073e+09 | I100: 0 | J100: 0 | K100: 0 | L100: 0 | M100: =H100-I100 | N100: =I100-J100 | O100: =J100-K100 | P100: =IFERROR(J100/H100,"") | Q100: =IFERROR(L100/H100,"") | R100: Sin contratos | U100: RENDIMIENTOS O RECURSOS DEL BALANCE DE PRESTACION DEL SERVICIO
A101: RENDIMIENTOS O RECURSOS DEL BALANCE DE PRESTACION DEL SERVICIO | B101: Nomina y aportes | C101: 02.01.2.3.1.01.01.001.01.007 | D101: 6809 | E101: Sueldo Docentes Con Situación de Fondos | F101: 1.3.3.6.01.1 | G101: R.B. SGP-EDUCACION-PRESTACIÃ¿N DE SERVICIO EDUCATIVO | H101: 91393157 | I101: 0 | J101: 0 | K101: 0 | L101: 0 | M101: =H101-I101 | N101: =I101-J101 | O101: =J101-K101 | P101: =IFERROR(J101/H101,"") | Q101: =IFERROR(L101/H101,"") | R101: Sin contratos | U101: RENDIMIENTOS O RECURSOS DEL BALANCE DE PRESTACION DEL SERVICIO
A102: RENDIMIENTOS O RECURSOS DEL BALANCE DE PRESTACION DEL SERVICIO | B102: Nomina y aportes | C102: 02.01.2.3.1.01.02.002.005 | D102: 4915 | E102: Aportes Patronales previsión social SSF Vig-2024 | F102: 1.2.4.1.01 | G102: SGP-EDUCACION-PRESTACION DE SERVICIOS | H102: 6058404770 | I102: 740190128 | J102: 740190128 | K102: 740190128 | L102: 740190128 | M102: =H102-I102 | N102: =I102-J102 | O102: =J102-K102 | P102: =IFERROR(J102/H102,"") | Q102: =IFERROR(L102/H102,"") | R102: Sin contratos | U102: RENDIMIENTOS O RECURSOS DEL BALANCE DE PRESTACION DEL SERVICIO
A103: SUBTOTAL RENDIMIENTOS O RECURSOS DEL BALANCE DE PRESTACION DEL SERVICIO | H103: =SUM(H100:H102) | I103: =SUM(I100:I102) | J103: =SUM(J100:J102) | K103: =SUM(K100:K102) | L103: =SUM(L100:L102) | M103: =H103-I103 | N103: =I103-J103 | O103: =J103-K103 | P103: =IFERROR(J103/H103,0) | Q103: =IFERROR(L103/H103,0)
A104: CALIDAD MATRICULA | B104: Inversion / proyectos | C104: 02.01.2.3.2.02.01.003.002 | D104: 4961 | E104: Dotación Institucional de Material y medios pedagógicos | F104: 1.2.4.1.03 | G104: SGP-EDUCACION-CALIDAD POR MATRICULA OFICIAL | H104: 85600000 | I104: 0 | J104: 0 | K104: 0 | L104: 0 | M104: =H104-I104 | N104: =I104-J104 | O104: =J104-K104 | P104: =IFERROR(J104/H104,"") | Q104: =IFERROR(L104/H104,"") | R104: Sin contratos | U104: CALIDAD MATRICULA
A105: CALIDAD MATRICULA | B105: Inversion / proyectos | C105: 02.01.2.3.2.02.01.003.010 | D105: 4962 | E105: Mantenimiento de Infraestructura Educativa | F105: 1.2.4.1.03 | G105: SGP-EDUCACION-CALIDAD POR MATRICULA OFICIAL | H105: 587806717 | I105: 0 | J105: 0 | K105: 0 | L105: 0 | M105: =H105-I105 | N105: =I105-J105 | O105: =J105-K105 | P105: =IFERROR(J105/H105,"") | Q105: =IFERROR(L105/H105,"") | R105: Sin contratos | U105: CALIDAD MATRICULA
A106: CALIDAD MATRICULA | B106: Inversion / proyectos | C106: 02.01.2.3.2.02.02.005.001 | D106: 5709 | E106: 020103 Mantenimiento de Infraestructura Educativa | F106: 1.2.4.3.03 | G106: SGP-PROPOSITO GENERAL-PROPOSITO GENERAL LIBRE INVERSION | H106: 1655693707 | I106: 1655693707 | J106: 1655693707 | K106: 1081507259 | L106: 1081507259 | M106: =H106-I106 | N106: =I106-J106 | O106: =J106-K106 | P106: =IFERROR(J106/H106,"") | Q106: =IFERROR(L106/H106,"") | R106: Sin contratos | U106: CALIDAD MATRICULA
A107: CALIDAD MATRICULA | B107: Inversion / proyectos | C107: 02.01.2.3.2.02.02.005.002 | D107: 6810 | E107: 020103 Mantenimiento de Infraestructura Educativa | F107: 1.3.3.6.03 | G107: R.B. SGP-EDUCACION-CALIDAD POR MATRICULA OFICIAL | H107: 0 | I107: 0 | J107: 0 | K107: 0 | L107: 0 | M107: =H107-I107 | N107: =I107-J107 | O107: =J107-K107 | P107: =IFERROR(J107/H107,"") | Q107: =IFERROR(L107/H107,"") | R107: Sin contratos | U107: CALIDAD MATRICULA
A108: CALIDAD MATRICULA | B108: Inversion / proyectos | C108: 02.01.2.3.2.02.02.005.003 | D108: 6811 | E108: 020103 Mantenimiento de Infraestructura Educativa | F108: 1.3.3.6.03.1 | G108: R.B. SGP-EDUCACION-CALIDAD POR MATRICULA OFICIAL | H108: 0 | I108: 0 | J108: 0 | K108: 0 | L108: 0 | M108: =H108-I108 | N108: =I108-J108 | O108: =J108-K108 | P108: =IFERROR(J108/H108,"") | Q108: =IFERROR(L108/H108,"") | R108: Sin contratos | U108: CALIDAD MATRICULA
A109: CALIDAD MATRICULA | B109: Inversion / proyectos | C109: 02.01.2.3.2.02.02.009.032 | D109: 4968 | E109: Fortalecimiento de estrategias para la permanencia escolar | F109: 1.2.4.1.03 | G109: SGP-EDUCACION-CALIDAD POR MATRICULA OFICIAL | H109: 58850000 | I109: 0 | J109: 0 | K109: 0 | L109: 0 | M109: =H109-I109 | N109: =I109-J109 | O109: =J109-K109 | P109: =IFERROR(J109/H109,"") | Q109: =IFERROR(L109/H109,"") | R109: Sin contratos | U109: CALIDAD MATRICULA
A110: CALIDAD MATRICULA | B110: Inversion / proyectos | C110: 02.01.2.3.2.02.02.009.033 | D110: 4969 | E110: Servicios públicos instituciones educativas | F110: 1.2.4.1.03 | G110: SGP-EDUCACION-CALIDAD POR MATRICULA OFICIAL | H110: 363800000 | I110: 363800000 | J110: 42448133 | K110: 42448133 | L110: 0 | M110: =H110-I110 | N110: =I110-J110 | O110: =J110-K110 | P110: =IFERROR(J110/H110,"") | Q110: =IFERROR(L110/H110,"") | R110: Sin contratos | U110: CALIDAD MATRICULA
A111: CALIDAD MATRICULA | B111: Inversion / proyectos | C111: 02.01.2.3.2.02.02.009.086 | D111: 4975 | E111: Capacitacion de docentes y directivos docentes | F111: 1.2.4.1.03 | G111: SGP-EDUCACION-CALIDAD POR MATRICULA OFICIAL | H111: 304950000 | I111: 0 | J111: 0 | K111: 0 | L111: 0 | M111: =H111-I111 | N111: =I111-J111 | O111: =J111-K111 | P111: =IFERROR(J111/H111,"") | Q111: =IFERROR(L111/H111,"") | R111: Sin contratos | U111: CALIDAD MATRICULA
A112: CALIDAD MATRICULA | B112: Inversion / proyectos | C112: 02.01.2.3.2.02.02.009.093 | D112: 5642 | E112: RB SGP-EDUCACION-CALIDAD POR MATRICULA OFICIAL | F112: 1.3.3.6.03 | G112: R.B. SGP-EDUCACION-CALIDAD POR MATRICULA OFICIAL | H112: 9.9954893e+08 | I112: 9.8954893e+08 | J112: 14000000 | K112: 14000000 | L112: 14000000 | M112: =H112-I112 | N112: =I112-J112 | O112: =J112-K112 | P112: =IFERROR(J112/H112,"") | Q112: =IFERROR(L112/H112,"") | R112: Sin contratos | U112: CALIDAD MATRICULA
A113: CALIDAD MATRICULA | B113: Inversion / proyectos | C113: 02.01.2.3.2.02.02.009.096 | D113: 5645 | E113: RB RF SGP - EDUCACION-CALIDAD POR MATRICULA OFICIAL | F113: 1.3.3.6.03.1 | G113: R.B. SGP-EDUCACION-CALIDAD POR MATRICULA OFICIAL | H113: 13674934 | I113: 13674934 | J113: 0 | K113: 0 | L113: 0 | M113: =H113-I113 | N113: =I113-J113 | O113: =J113-K113 | P113: =IFERROR(J113/H113,"") | Q113: =IFERROR(L113/H113,"") | R113: Sin contratos | U113: CALIDAD MATRICULA
A114: CALIDAD MATRICULA | B114: Inversion / proyectos | C114: 02.01.2.3.2.02.02.009.111 | D114: 5828 | E114: RF SGP- Calidad Matricula | F114: 1.3.2.2.03 | G114: R.F. SGP - EDUCACION-CALIDAD POR MATRICULA OFICIAL | H114: 0 | I114: 0 | J114: 0 | K114: 0 | L114: 0 | M114: =H114-I114 | N114: =I114-J114 | O114: =J114-K114 | P114: =IFERROR(J114/H114,"") | Q114: =IFERROR(L114/H114,"") | R114: Sin contratos | U114: CALIDAD MATRICULA
A115: SUBTOTAL CALIDAD MATRICULA | H115: =SUM(H104:H114) | I115: =SUM(I104:I114) | J115: =SUM(J104:J114) | K115: =SUM(K104:K114) | L115: =SUM(L104:L114) | M115: =H115-I115 | N115: =I115-J115 | O115: =J115-K115 | P115: =IFERROR(J115/H115,0) | Q115: =IFERROR(L115/H115,0)
A116: CALIDAD GRATUIDAD | B116: Inversion / proyectos | C116: 02.01.2.3.2.02.02.009.034 | D116: 4970 | E116: Fondos de Servicios Educativos de las Instituciones de Preescolar, básica y Media | F116: 1.2.4.1.04 | G116: SGP-EDUCACION-CALIDAD POR GRATUIDAD | H116: 2676056094 | I116: 2310562061 | J116: 2310562061 | K116: 2310562061 | L116: 2310562061 | M116: =H116-I116 | N116: =I116-J116 | O116: =J116-K116 | P116: =IFERROR(J116/H116,"") | Q116: =IFERROR(L116/H116,"") | R116: Sin contratos | U116: CALIDAD GRATUIDAD
A117: SUBTOTAL CALIDAD GRATUIDAD | H117: =SUM(H116:H116) | I117: =SUM(I116:I116) | J117: =SUM(J116:J116) | K117: =SUM(K116:K116) | L117: =SUM(L116:L116) | M117: =H117-I117 | N117: =I117-J117 | O117: =J117-K117 | P117: =IFERROR(J117/H117,0) | Q117: =IFERROR(L117/H117,0)
A118: SGP - PGN - PAE | B118: Inversion / proyectos | C118: 02.01.2.3.2.02.02.009.021 | D118: 6821 | E118: ECB RES 295 NOV 05 2021 MINEDUCACIÓN PROGRAMA DE ALIMENTACIÓN ESCOLAR PAE | F118: 1.3.3.5.04.01 | G118: R.B. OTRAS TRANSFERENCIAS CORRIENTES DE OTRAS ENTIDADES DEL GOBIERNO GENERAL | H118: 0.89 | I118: 0 | J118: 0 | K118: 0 | L118: 0 | M118: =H118-I118 | N118: =I118-J118 | O118: =J118-K118 | P118: =IFERROR(J118/H118,"") | Q118: =IFERROR(L118/H118,"") | R118: Sin contratos | U118: SGP - PGN - PAE
A119: SGP - PGN - PAE | B119: Inversion / proyectos | C119: 02.01.2.3.2.02.02.009.024 | D119: 6807 | E119: 020106 Mejoramiento de la cobertura Educativa PAE | F119: 1.3.3.9.01.1 | G119: R.B. SGP-ASIGNACION ESPECIAL-PROGRAMAS DE ALIMENTACION ESCOLAR | H119: 1352967.4 | I119: 0 | J119: 0 | K119: 0 | L119: 0 | M119: =H119-I119 | N119: =I119-J119 | O119: =J119-K119 | P119: =IFERROR(J119/H119,"") | Q119: =IFERROR(L119/H119,"") | R119: Sin contratos | U119: SGP - PGN - PAE
A120: SGP - PGN - PAE | B120: Inversion / proyectos | C120: 02.01.2.3.2.02.02.009.025 | D120: 6806 | E120: 020106 Mejoramiento de la cobertura Educativa PAE | F120: 1.3.3.5.03 | G120: R.B. APORTES NACION - ALIMENTACION ESCOLAR | H120: 3.1169778e+08 | I120: 2.5451226e+08 | J120: 2.5451226e+08 | K120: 2.5451226e+08 | L120: 2.5451226e+08 | M120: =H120-I120 | N120: =I120-J120 | O120: =J120-K120 | P120: =IFERROR(J120/H120,"") | Q120: =IFERROR(L120/H120,"") | R120: 1 contrato | $254,512,257 comprometido | U120: SGP - PGN - PAE
A121: SGP - PGN - PAE | B121: Inversion / proyectos | C121: 02.01.2.3.2.02.02.009.035 | D121: 4983 | E121: 020106 Mejoramiento de la cobertura Educativa PAE | F121: 1.2.4.4.01 | G121: SGP-ASIGNACION ESPECIAL-PROGRAMAS DE ALIMENTACION ESCOLAR | H121: 452393559 | I121: 452393559 | J121: 452393559 | K121: 278624292 | L121: 278624292 | M121: =H121-I121 | N121: =I121-J121 | O121: =J121-K121 | P121: =IFERROR(J121/H121,"") | Q121: =IFERROR(L121/H121,"") | R121: 1 contrato | $173,769,267 comprometido | U121: SGP - PGN - PAE
A122: SGP - PGN - PAE | B122: Inversion / proyectos | C122: 02.01.2.3.2.02.02.009.087 | D122: 5635 | E122: RB RF SGP - ASIGNACION ESPECIAL-PROGRAMAS DE ALIMENTACION ESCOLAR | F122: 1.3.3.9.01.1 | G122: R.B. SGP-ASIGNACION ESPECIAL-PROGRAMAS DE ALIMENTACION ESCOLAR | H122: 0 | I122: 0 | J122: 0 | K122: 0 | L122: 0 | M122: =H122-I122 | N122: =I122-J122 | O122: =J122-K122 | P122: =IFERROR(J122/H122,"") | Q122: =IFERROR(L122/H122,"") | R122: Sin contratos | U122: SGP - PGN - PAE
A123: SGP - PGN - PAE | B123: Inversion / proyectos | C123: 02.01.2.3.2.02.02.009.098 | D123: 5648 | E123: ECB RES 295 NOV 05 2021 MINEDUCACIÓN PROGRAMA DE ALIMENTACIÓN ESCOLAR PAE | F123: 1.3.3.5.04.01 | G123: R.B. OTRAS TRANSFERENCIAS CORRIENTES DE OTRAS ENTIDADES DEL GOBIERNO GENERAL | H123: 0 | I123: 0 | J123: 0 | K123: 0 | L123: 0 | M123: =H123-I123 | N123: =I123-J123 | O123: =J123-K123 | P123: =IFERROR(J123/H123,"") | Q123: =IFERROR(L123/H123,"") | R123: Sin contratos | U123: SGP - PGN - PAE
A124: SGP - PGN - PAE | B124: Inversion / proyectos | C124: 02.01.2.3.2.02.02.009.101 | D124: 5651 | E124: RES 388 DEL 17 NOV DE 2023 PROGR ALIMENTAC ESCOLAR PAE | F124: 1.2.3.3.03 | G124: APORTES NACION - ALIMENTACION ESCOLAR | H124: 3629344950 | I124: 3629344950 | J124: 3399333000 | K124: 3364384856 | L124: 3364384856 | M124: =H124-I124 | N124: =I124-J124 | O124: =J124-K124 | P124: =IFERROR(J124/H124,"") | Q124: =IFERROR(L124/H124,"") | R124: Sin contratos | U124: SGP - PGN - PAE
A125: SGP - PGN - PAE | B125: Inversion / proyectos | C125: 02.01.2.3.2.02.02.009.112 | D125: 5829 | E125: RF Recursos SGP Alimentación Escolar | F125: 1.3.2.2.09 | G125: R.F. SGP - ASIGNACION ESPECIAL-PROGRAMAS DE ALIMENTACION ESCOLAR | H125: 0 | I125: 0 | J125: 0 | K125: 0 | L125: 0 | M125: =H125-I125 | N125: =I125-J125 | O125: =J125-K125 | P125: =IFERROR(J125/H125,"") | Q125: =IFERROR(L125/H125,"") | R125: Sin contratos | U125: SGP - PGN - PAE
A126: SGP - PGN - PAE | B126: Inversion / proyectos | C126: 02.01.2.3.2.02.02.009.114 | D126: 6882 | E126: 020106 RF Mejoramiento de la cobertura Educativa PAE | F126: 1.3.2.2.09 | G126: R.F. SGP - ASIGNACION ESPECIAL-PROGRAMAS DE ALIMENTACION ESCOLAR | H126: 856052 | I126: 0 | J126: 0 | K126: 0 | L126: 0 | M126: =H126-I126 | N126: =I126-J126 | O126: =J126-K126 | P126: =IFERROR(J126/H126,"") | Q126: =IFERROR(L126/H126,"") | R126: Sin contratos | U126: SGP - PGN - PAE
A127: SGP - PGN - PAE | B127: Inversion / proyectos | C127: 02.01.2.3.2.02.02.009.115 | D127: 6883 | E127: 020106 RF LI Mejoramiento de la cobertura Educativa PAE | F127: 1.3.2.2.08 | G127: R.F. SGP - PROPOSITO GENERAL | H127: 3120955 | I127: 0 | J127: 0 | K127: 0 | L127: 0 | M127: =H127-I127 | N127: =I127-J127 | O127: =J127-K127 | P127: =IFERROR(J127/H127,"") | Q127: =IFERROR(L127/H127,"") | R127: Sin contratos | U127: SGP - PGN - PAE
A128: SUBTOTAL SGP - PGN - PAE | H128: =SUM(H118:H127) | I128: =SUM(I118:I127) | J128: =SUM(J118:J127) | K128: =SUM(K118:K127) | L128: =SUM(L118:L127) | M128: =H128-I128 | N128: =I128-J128 | O128: =J128-K128 | P128: =IFERROR(J128/H128,0) | Q128: =IFERROR(L128/H128,0)
A129: PRIMERA INFANCIA | B129: Inversion / proyectos | C129: 01.01.2.3.2.02.02.009.036 | D129: 6848 | E129: 010101 Acompañamiento en la atención a la primera infancia | F129: 1.2.1.0.00 | G129: INGRESOS CORRIENTES DE LIBRE DESTINACION | H129: 2.7267325e+09 | I129: 1555487503 | J129: 1555487503 | K129: 0 | L129: 0 | M129: =H129-I129 | N129: =I129-J129 | O129: =J129-K129 | P129: =IFERROR(J129/H129,"") | Q129: =IFERROR(L129/H129,"") | R129: 1 contrato | $1,555,487,503 comprometido | U129: PRIMERA INFANCIA
A130: PRIMERA INFANCIA | B130: Inversion / proyectos | C130: 02.01.2.3.2.02.02.009.088 | D130: 5636 | E130: RB RF SGP - ASIGNACION-ATENCION INTEGRAL DE LA PRIMERA INFANCIA | F130: 1.3.3.9.03.1 | G130: R.B. SGP-ASIGNACION-ATENCION INTEGRAL DE LA PRIMERA INFANCIA | H130: 2195.65 | I130: 0 | J130: 0 | K130: 0 | L130: 0 | M130: =H130-I130 | N130: =I130-J130 | O130: =J130-K130 | P130: =IFERROR(J130/H130,"") | Q130: =IFERROR(L130/H130,"") | R130: Sin contratos | U130: PRIMERA INFANCIA
A131: PRIMERA INFANCIA | B131: Inversion / proyectos | C131: 02.01.2.3.2.02.02.009.089 | D131: 5637 | E131: RB SGP-ASIGNACION-ATENCION INTEGRAL DE LA PRIMERA INFANCIA | F131: 1.3.3.9.03 | G131: R.B. SGP-ASIGNACION-ATENCION INTEGRAL DE LA PRIMERA INFANCIA | H131: 364571.98 | I131: 0 | J131: 0 | K131: 0 | L131: 0 | M131: =H131-I131 | N131: =I131-J131 | O131: =J131-K131 | P131: =IFERROR(J131/H131,"") | Q131: =IFERROR(L131/H131,"") | R131: Sin contratos | U131: PRIMERA INFANCIA
A132: SUBTOTAL PRIMERA INFANCIA | H132: =SUM(H129:H131) | I132: =SUM(I129:I131) | J132: =SUM(J129:J131) | K132: =SUM(K129:K131) | L132: =SUM(L129:L131) | M132: =H132-I132 | N132: =I132-J132 | O132: =J132-K132 | P132: =IFERROR(J132/H132,0) | Q132: =IFERROR(L132/H132,0)
A133: INFRAESTRUCTURA | B133: Inversion / proyectos | C133: 02.01.2.3.2.02.02.005.004 | D133: 6814 | E133: RF CI 1878 NOV 10 VF 2022 MINIST INTERIOR FONSECON SACUDETE AL PARQUE TIPO 2 | F133: 1.3.2.3.11.4.2 | G133: OTROS RENDIMIENTOS FINANCIEROS | H133: 4914169.4 | I133: 0 | J133: 0 | K133: 0 | L133: 0 | M133: =H133-I133 | N133: =I133-J133 | O133: =J133-K133 | P133: =IFERROR(J133/H133,"") | Q133: =IFERROR(L133/H133,"") | R133: Sin contratos | U133: INFRAESTRUCTURA
A134: INFRAESTRUCTURA | B134: Inversion / proyectos | C134: 02.01.2.3.2.02.02.005.005 | D134: 6815 | E134: 020103 CI 1878 NOV 10 VF 2022 MINIST INTERIOR FONSECON SACUDETE AL PARQUE TIPO 2 | F134: 1.3.3.5.04.01 | G134: R.B. OTRAS TRANSFERENCIAS CORRIENTES DE OTRAS ENTIDADES DEL GOBIERNO GENERAL | H134: 42607853 | I134: 0 | J134: 0 | K134: 0 | L134: 0 | M134: =H134-I134 | N134: =I134-J134 | O134: =J134-K134 | P134: =IFERROR(J134/H134,"") | Q134: =IFERROR(L134/H134,"") | R134: Sin contratos | U134: INFRAESTRUCTURA
A135: INFRAESTRUCTURA | B135: Inversion / proyectos | C135: 02.01.2.3.2.02.02.009.097 | D135: 5647 | E135: ECB RF CI 1878 NOV 10 VF 2022 MINIST INTERIOR FONSECON SACUDETE AL PARQUE TIPO 2 | F135: 1.3.3.5.04.01 | G135: R.B. OTRAS TRANSFERENCIAS CORRIENTES DE OTRAS ENTIDADES DEL GOBIERNO GENERAL | H135: 0 | I135: 0 | J135: 0 | K135: 0 | L135: 0 | M135: =H135-I135 | N135: =I135-J135 | O135: =J135-K135 | P135: =IFERROR(J135/H135,"") | Q135: =IFERROR(L135/H135,"") | R135: Sin contratos | U135: INFRAESTRUCTURA
A136: INFRAESTRUCTURA | B136: Inversion / proyectos | C136: 02.01.2.3.2.02.02.009.102 | D136: 5652 | E136: DC CI 1878 NOV 10 VF 2022 MINIST INTERIOR FONSECON SACUDETE AL PARQUE TIPO 2 | F136: 1.2.3.3.04.01 | G136: OTRAS TRANSFERENCIAS CORRIENTES DE OTRAS ENTIDADES CON DESTINACION ESPECIFICA LEGAL DEL GOBIERNO GENERAL | H136: 4.2904941e+08 | I136: 0 | J136: 0 | K136: 0 | L136: 0 | M136: =H136-I136 | N136: =I136-J136 | O136: =J136-K136 | P136: =IFERROR(J136/H136,"") | Q136: =IFERROR(L136/H136,"") | R136: Sin contratos | U136: INFRAESTRUCTURA
A137: SUBTOTAL INFRAESTRUCTURA | H137: =SUM(H133:H136) | I137: =SUM(I133:I136) | J137: =SUM(J133:J136) | K137: =SUM(K133:K136) | L137: =SUM(L133:L136) | M137: =H137-I137 | N137: =I137-J137 | O137: =J137-K137 | P137: =IFERROR(J137/H137,0) | Q137: =IFERROR(L137/H137,0)
A138: VIGENCIAS ANTERIORES | B138: Inversion / proyectos | C138: 02.01.2.3.2.02.02.009.022 | D138: 6820 | E138: ECB RF COFINANCIACIÓN DEL MEN | F138: 1.3.3.5.04.01 | G138: R.B. OTRAS TRANSFERENCIAS CORRIENTES DE OTRAS ENTIDADES DEL GOBIERNO GENERAL | H138: 727396.07 | I138: 0 | J138: 0 | K138: 0 | L138: 0 | M138: =H138-I138 | N138: =I138-J138 | O138: =J138-K138 | P138: =IFERROR(J138/H138,"") | Q138: =IFERROR(L138/H138,"") | R138: Sin contratos | U138: VIGENCIAS ANTERIORES
A139: VIGENCIAS ANTERIORES | B139: Inversion / proyectos | C139: 02.01.2.3.2.02.02.009.023 | D139: 6818 | E139: ECB APORTES NACIONALES (CONVENIOS ANTIGUOS) | F139: 1.3.3.5.04.01 | G139: R.B. OTRAS TRANSFERENCIAS CORRIENTES DE OTRAS ENTIDADES DEL GOBIERNO GENERAL | H139: 7392767 | I139: 0 | J139: 0 | K139: 0 | L139: 0 | M139: =H139-I139 | N139: =I139-J139 | O139: =J139-K139 | P139: =IFERROR(J139/H139,"") | Q139: =IFERROR(L139/H139,"") | R139: Sin contratos | U139: VIGENCIAS ANTERIORES
A140: VIGENCIAS ANTERIORES | B140: Inversion / proyectos | C140: 02.01.2.3.2.02.02.009.090 | D140: 5638 | E140: RB OTROS COMPUTADORES EDUC VIG 2016 | F140: 1.3.3.5.04.06 | G140: R.B. OTRAS TRANSFERENCIAS CORRIENTES DE OTRAS ENTIDADES DEL GOBIERNO GENERAL | H140: 4910052.1 | I140: 4910052.1 | J140: 0 | K140: 0 | L140: 0 | M140: =H140-I140 | N140: =I140-J140 | O140: =J140-K140 | P140: =IFERROR(J140/H140,"") | Q140: =IFERROR(L140/H140,"") | R140: Sin contratos | U140: VIGENCIAS ANTERIORES
A141: VIGENCIAS ANTERIORES | B141: Inversion / proyectos | C141: 02.01.2.3.2.02.02.009.100 | D141: 5650 | E141: ECB RF COFINANCIACIÓN DEL MEN | F141: 1.3.3.5.04.01 | G141: R.B. OTRAS TRANSFERENCIAS CORRIENTES DE OTRAS ENTIDADES DEL GOBIERNO GENERAL | H141: 0 | I141: 0 | J141: 0 | K141: 0 | L141: 0 | M141: =H141-I141 | N141: =I141-J141 | O141: =J141-K141 | P141: =IFERROR(J141/H141,"") | Q141: =IFERROR(L141/H141,"") | R141: Sin contratos | U141: VIGENCIAS ANTERIORES
A142: VIGENCIAS ANTERIORES | B142: Inversion / proyectos | C142: 02.01.2.3.2.02.02.009.113 | D142: 5830 | E142: R.F. OTROS C.I COMPUT. PARA EDU VIG 2016 | F142: 1.3.2.3.11.13| | G142: OTROS RENDIMIENTOS FINANCIEROS | H142: 64479 | I142: 64479 | J142: 0 | K142: 0 | L142: 0 | M142: =H142-I142 | N142: =I142-J142 | O142: =J142-K142 | P142: =IFERROR(J142/H142,"") | Q142: =IFERROR(L142/H142,"") | R142: Sin contratos | U142: VIGENCIAS ANTERIORES
A143: SUBTOTAL VIGENCIAS ANTERIORES | H143: =SUM(H138:H142) | I143: =SUM(I138:I142) | J143: =SUM(J138:J142) | K143: =SUM(K138:K142) | L143: =SUM(L138:L142) | M143: =H143-I143 | N143: =I143-J143 | O143: =J143-K143 | P143: =IFERROR(J143/H143,0) | Q143: =IFERROR(L143/H143,0)
A144: TOTAL GENERAL | H144: =SUM(H83,H99,H103,H115,H117,H128,H132,H137,H143) | I144: =SUM(I83,I99,I103,I115,I117,I128,I132,I137,I143) | J144: =SUM(J83,J99,J103,J115,J117,J128,J132,J137,J143) | K144: =SUM(K83,K99,K103,K115,K117,K128,K132,K137,K143) | L144: =SUM(L83,L99,L103,L115,L117,L128,L132,L137,L143) | M144: =H144-I144 | N144: =I144-J144 | O144: =J144-K144 | P144: =IFERROR(J144/H144,0) | Q144: =IFERROR(L144/H144,0)

Sheet CONTRATOS
A1: Nro contrato | B1: Contratista | C1: Objeto | D1: cons_ppt | E1: Proyecto / Rubro | F1: Componente | G1: Fuente | H1: Valor contrato | I1: Comprometido | J1: Obligado | K1: Pagado | L1: Saldo x pagar | M1: % Ejec | N1: CDP | O1: RP | P1: Vig Futura | Q1: Estado | R1: Match | S1: Suscripcion | T1: Supervisor | U1: Observacion
A2: 10.14.00.00-22.15-006-2026 | B2: EQS DOTACIONES | D2: 4959 | E2: Dotación Ley 70/88 Docentes | F2: PRESTACION DEL SERVICIO | G2: SGP-EDUCACION-PRESTACION DE SERVICIOS | H2: 18018000 | I2: 18018000 | J2: 0 | K2: 0 | L2: 18018000 | M2: 0 | N2: 377 | R2: OK - match unico por # de CDP
A3: 10.14.00.00-23.01-009-2026 | B3: UNIÓN TEMPORAL OPERACIÓN EDUCATIVA RIONEGRO (I.E) | D3: 4963 | E3: Fortalecimiento de estrategias para la permanencia escolar svc aseo | F3: PRESTACION DEL SERVICIO | G3: SGP-EDUCACION-PRESTACION DE SERVICIOS | H3: 6616274792 | I3: 759871200 | J3: 0 | K3: 0 | L3: 6616274792 | M3: 0 | N3: 474 | R3: OK - match por CDP + codigo (CDP compartido)
A4: 10.14.00.00-21.12-007-2026 | B4: WPR GESTION EN SALUD S.A.S | D4: 4967 | E4: Atención a población con necesidades especiales o discapacidades | F4: PRESTACION DEL SERVICIO | G4: SGP-EDUCACION-PRESTACION DE SERVICIOS | H4: 4280761543 | I4: 379869229 | J4: 0 | K4: 379869229 | L4: 3900892314 | M4: 0.088738703 | N4: 196 | R4: OK - match por CDP + codigo (CDP compartido)
A5: 10.13.00-22.01-006-2025 | B5: EQUIDE SER | D5: 4972 | E5: 020101 VF Fortalecimiento de la pertinencia y la calidad educativa | F5: RECURSOS PROPIOS O LIBRE INVERSION | G5: INGRESOS CORRIENTES DE LIBRE DESTINACION | H5: 0 | I5: 1329649621 | J5: 0 | K5: 1329649621 | L5: -1329649621 | M5: — | N5: 28 | R5: OK - match unico por # de CDP
A6: 1120-07-021-2024 Esal 018 2024 | B6: EQUIDE I.E 2024-2025 | D6: 4972 | E6: 020101 VF Fortalecimiento de la pertinencia y la calidad educativa | F6: RECURSOS PROPIOS O LIBRE INVERSION | G6: INGRESOS CORRIENTES DE LIBRE DESTINACION | H6: 0 | I6: 1572774586 | J6: 0 | K6: 1572774586 | L6: -1572774586 | M6: — | N6: 29 | R6: OK - match unico por # de CDP
A7: 10.14.00.00-21.12-017-2026 | B7: GMA DIGITAL S.A.S. | D7: 4973 | E7: 020101 Fortalecimiento de la pertinencia y la calidad educativa | F7: RECURSOS PROPIOS O LIBRE INVERSION | G7: INGRESOS CORRIENTES DE LIBRE DESTINACION | H7: 20306000 | I7: 20306000 | J7: 0 | K7: 13032211 | L7: 7273789 | M7: 0.64179115 | N7: 30 | R7: OK - match unico por # de CDP
A8: 10.14.00.00-21.16-003-2026 | B8: UNIÓN TEMPORAL UDEA E INSTITUTO PARA EL DESARROLLO DE ANTIOQUIA -IDEA | D8: 4980 | E8: 020104 Fortalecimiento de la Educación técnica, tecnológica y superior | F8: RECURSOS PROPIOS O LIBRE INVERSION | G8: INGRESOS CORRIENTES DE LIBRE DESTINACION | H8: 849004703 | I8: 849004703 | J8: 0 | K8: 621845949 | L8: 227158754 | M8: 0.73244111 | N8: 269 | R8: OK - match unico por # de CDP
A9: 10.13.00-21.16-041-2025 | B9: NUTRICERES NUEVO 2025-2026 | D9: 4985 | E9: 020106 Mejoramiento de la cobertura Educativa PAE | F9: RECURSOS PROPIOS O LIBRE INVERSION | G9: INGRESOS CORRIENTES DE LIBRE DESTINACION | H9: 0 | I9: 26890794978 | J9: 0 | K9: 7798093002 | L9: -7798093002 | M9: — | N9: 136 | R9: OK - match por CDP + codigo (CDP compartido)
A10: 10.14.00.00-21.12-008-2026 | B10: Juan Camilo Restrepo Rodriguez | D10: 4985 | E10: 020106 Mejoramiento de la cobertura Educativa PAE | F10: RECURSOS PROPIOS O LIBRE INVERSION | G10: INGRESOS CORRIENTES DE LIBRE DESTINACION | H10: 72879048 | I10: 72879048 | J10: 0 | K10: 48365186 | L10: 24513862 | M10: 0.66363636 | N10: 26 | R10: OK - match unico por # de CDP
A11: 10.14.00.00-21.12-009-2026 | B11: Ana Cecilia Franco Marin | D11: 4985 | E11: 020106 Mejoramiento de la cobertura Educativa PAE | F11: RECURSOS PROPIOS O LIBRE INVERSION | G11: INGRESOS CORRIENTES DE LIBRE DESTINACION | H11: 63373090 | I11: 63373090 | J11: 0 | K11: 42056687 | L11: 21316403 | M11: 0.66363636 | N11: 23 | R11: OK - match unico por # de CDP
A12: 10.14.00.00-21.12-014-2026 | B12: Maria Fernanda Montoya Guarin | D12: 4985 | E12: 020106 Mejoramiento de la cobertura Educativa PAE | F12: RECURSOS PROPIOS O LIBRE INVERSION | G12: INGRESOS CORRIENTES DE LIBRE DESTINACION | H12: 63373090 | I12: 63373090 | J12: 0 | K12: 42056687 | L12: 21316403 | M12: 0.66363636 | N12: 22 | R12: OK - match unico por # de CDP
A13: 10.14.00.00-21.12-015-2026 | B13: Andrés Felipe Pardo Martínez | D13: 4985 | E13: 020106 Mejoramiento de la cobertura Educativa PAE | F13: RECURSOS PROPIOS O LIBRE INVERSION | G13: INGRESOS CORRIENTES DE LIBRE DESTINACION | H13: 63373090 | I13: 63373090 | J13: 0 | K13: 42056687 | L13: 21316403 | M13: 0.66363636 | N13: 27 | R13: OK - match unico por # de CDP
A14: 10.14.00.00-21.12-016-2026 | B14: Maria Catherine Soto Garcia | D14: 4985 | E14: 020106 Mejoramiento de la cobertura Educativa PAE | F14: RECURSOS PROPIOS O LIBRE INVERSION | G14: INGRESOS CORRIENTES DE LIBRE DESTINACION | H14: 63373090 | I14: 63373090 | J14: 0 | K14: 42056687 | L14: 21316403 | M14: 0.66363636 | N14: 24 | R14: OK - match unico por # de CDP
A15: 10.13.00-21.16-015-2025 | B15: NUTRICERES (Paquetes) | D15: 4986 | E15: 020106 Mejoramiento de la cobertura Educativa Paquetes PAE | F15: RECURSOS PROPIOS O LIBRE INVERSION | G15: INGRESOS CORRIENTES DE LIBRE DESTINACION | H15: 0 | I15: 3794269403 | J15: 0 | K15: 3411171557 | L15: -3411171557 | M15: — | N15: 135 | R15: OK - match unico por # de CDP
A16: 10.14.00.00-23.01-022-2026 ESAL 026 2026 | B16: COLOMBO AMERICANO MEDELLIN | D16: 4995 | E16: 020107 Fortalecimiento del programa de Bilinguismo | F16: RECURSOS PROPIOS O LIBRE INVERSION | G16: INGRESOS CORRIENTES DE LIBRE DESTINACION | H16: 941332078 | I16: 941332078 | J16: 0 | K16: 0 | L16: 941332078 | M16: 0 | N16: 375 | R16: OK - match unico por # de CDP
A17: 10.13.00-21.12-067-2025 | B17: COMFAMA | D17: 4996 | E17: 020108 Fortalecimiento del Bienestar Institucional | F17: RECURSOS PROPIOS O LIBRE INVERSION | G17: INGRESOS CORRIENTES DE LIBRE DESTINACION | H17: 0 | I17: 578755999 | J17: 0 | K17: 198002215 | L17: -198002215 | M17: — | N17: 171 | R17: OK - match unico por # de CDP
A18: 10.14.00.00-23.01-020-2026 | B18: EQUIDE SER (Administrativos) | D18: 4996 | E18: 020108 Fortalecimiento del Bienestar Institucional | F18: RECURSOS PROPIOS O LIBRE INVERSION | G18: INGRESOS CORRIENTES DE LIBRE DESTINACION | H18: 3381349180 | I18: 3381349180 | J18: 0 | K18: 0 | L18: 3381349180 | M18: 0 | N18: 897 | R18: OK - match unico por # de CDP
A19: 1120-07-021-2024 Esal 018 2024 | B19: EQUIDE I.E 2024-2025 | D19: 4996 | E19: 020108 Fortalecimiento del Bienestar Institucional | F19: RECURSOS PROPIOS O LIBRE INVERSION | G19: INGRESOS CORRIENTES DE LIBRE DESTINACION | H19: 0 | I19: 262129098 | J19: 0 | K19: 262129098 | L19: -262129098 | M19: — | N19: 566 | R19: OK - match unico por # de CDP
A20: 10.13.00-21.16-041-2025 | B20: NUTRICERES NUEVO 2025-2026 | D20: 4983 | E20: 020106 Mejoramiento de la cobertura Educativa PAE | F20: SGP - PGN - PAE | G20: SGP-ASIGNACION ESPECIAL-PROGRAMAS DE ALIMENTACION ESCOLAR | H20: 0 | I20: 173769267 | J20: 0 | K20: 0 | L20: 0 | M20: — | N20: 845 | R20: OK - match unico por # de CDP
A21: 10.13.00-21.16-041-2025 | B21: NUTRICERES NUEVO 2025-2026 | D21: 6806 | E21: 020106 Mejoramiento de la cobertura Educativa PAE | F21: SGP - PGN - PAE | G21: R.B. APORTES NACION - ALIMENTACION ESCOLAR | H21: 0 | I21: 2.5451226e+08 | J21: 0 | K21: 2.5451226e+08 | L21: -2.5451226e+08 | M21: — | N21: 483 | R21: OK - match unico por # de CDP
A22: 10.14.00.00-23.01-013-2026 | B22: CORPOASES - SALA CUNAS | D22: 6848 | E22: 010101 Acompañamiento en la atención a la primera infancia | F22: PRIMERA INFANCIA | G22: INGRESOS CORRIENTES DE LIBRE DESTINACION | H22: 1555487503 | I22: 1555487503 | J22: 0 | K22: 43727430 | L22: 1511760073 | M22: 0.028111721 | N22: 509 | R22: OK - match unico por # de CDP
A23: 1120-07-021-2024 Esal 018 2024 | B23: EQUIDE I.E 2024-2025 | D23: 3767 | F23: (otra Secretaria) | H23: 0 | I23: 710160000 | J23: 0 | K23: 7.1016e+08 | L23: -7.1016e+08 | M23: — | N23: 93 | R23: OK - match unico por # de CDP
A24: 10.13.00-21.12-067-2025 | B24: COMFAMA | D24: 3806 | F24: (otra Secretaria) | H24: 1268286939 | I24: 689530940 | J24: 0 | K24: 689530940 | L24: 578755999 | M24: 0.54367109 | N24: 1106 | R24: OK - match unico por # de CDP
A25: 10.14.00.00-21.16-069-2025 | B25: ESO RIONEGRO S.A.S | D25: 3806 | F25: (otra Secretaria) | H25: 356690601 | I25: 356690601 | J25: 0 | K25: 130015816 | L25: 226674785 | M25: 0.36450586 | N25: 421 | R25: OK - match unico por # de CDP
A26: 10.13.00-21.16-015-2025 | B26: NUTRICERES (Paquetes) | D26: 5317 | F26: (otra Secretaria) | H26: 11382808209 | I26: 7588538806 | J26: 0 | K26: 5029097642 | L26: 6353710567 | M26: 0.4418152 | N26: 218 | R26: OK - match unico por # de CDP
A27: 10.13.00-21.16-052-2025 | B27: CORPORACIÓN GILBERTO ECHEVERRI MEJÍA | D27: 6895 | F27: (otra Secretaria) | H27: 486556410 | I27: 220406565 | J27: 0 | K27: 166912664 | L27: 319643746 | M27: 0.34304895 | N27: 1107 | R27: OK - match unico por # de CDP
A28: 10.13.00-21.12-067-2025 | B28: COMFAMA | F28: (vigencia futura -- otro periodo) | H28: 0 | I28: 435682534 | J28: 0 | K28: 0 | L28: 0 | M28: — | N28: -20251106 | P28: 2025 | R28: Vigencia futura de otro periodo (normal)
A29: 10.13.00-21.16-015-2025 | B29: NUTRICERES (Paquetes) | F29: (vigencia futura -- otro periodo) | H29: 0 | I29: 2559441164 | J29: 0 | K29: 2559441164 | L29: -2559441164 | M29: — | N29: -2025218 | P29: 2025 | R29: Vigencia futura de otro periodo (normal)
A30: 10.13.00-21.16-041-2025 | B30: NUTRICERES NUEVO 2025-2026 | F30: (vigencia futura -- otro periodo) | H30: 0 | I30: 7.3477494e+09 | J30: 0 | K30: 0 | L30: 0 | M30: — | N30: -2025991 | P30: 2025 | R30: Vigencia futura de otro periodo (normal)
A31: 10.13.00-21.16-052-2025 | B31: CORPORACIÓN GILBERTO ECHEVERRI MEJÍA | F31: (vigencia futura -- otro periodo) | H31: 0 | I31: 220406565 | J31: 0 | K31: 0 | L31: 0 | M31: — | N31: -20251107 | P31: 2025 | R31: Vigencia futura de otro periodo (normal)
A32: 10.13.00-22.01-006-2025 | B32: EQUIDE SER | F32: (vigencia futura -- otro periodo) | H32: 0 | I32: 755745927 | J32: 0 | K32: 755745927 | L32: -755745927 | M32: — | N32: -20256 | P32: 2025 | R32: Vigencia futura de otro periodo (normal)
A33: 10.13.00-22.01-014-2025 | B33: EQUIDE ESAL 015 2025 (PLAN DECENAL) | F33: (vigencia futura -- otro periodo) | H33: 0 | I33: 104407076 | J33: 0 | K33: 0 | L33: 0 | M33: — | N33: -2025423 | P33: 2025 | R33: Vigencia futura de otro periodo (normal)
A34: 10.14.00.00-21.16-069-2025 | B34: ESO RIONEGRO S.A.S | F34: (vigencia futura -- otro periodo) | H34: 0 | I34: 226674785 | J34: 0 | K34: 47530294 | L34: -47530294 | M34: — | N34: -2025421 | P34: 2025 | R34: Vigencia futura de otro periodo (normal)
A35: 1120-07-021-2024 Esal 018 2024 | B35: EQUIDE I.E 2024-2025 | F35: (vigencia futura -- otro periodo) | H35: 8424574030 | I35: 150000000 | J35: 0 | K35: 150000000 | L35: 8274574030 | M35: 0.017805055 | N35: -20241412 | P35: 2024 | R35: Vigencia futura de otro periodo (normal)
A36: 1120-07-021-2024 Esal 018 2024 | B36: EQUIDE I.E 2024-2025 | F36: (vigencia futura -- otro periodo) | H36: 0 | I36: 257500313 | J36: 0 | K36: 257500313 | L36: -257500313 | M36: — | N36: -202593 | P36: 2025 | R36: Vigencia futura de otro periodo (normal)
A37: 10.13.00-21.16-041-2025 | B37: NUTRICERES NUEVO 2025-2026 | F37: (SIN RESOLVER -- revisar) | H37: 42991910142 | I37: 410795944 | J37: 0 | K37: 410795944 | L37: 42581114198 | M37: 0.0095551917 | N37: 991 | R37: AMBIGUO -- CDP compartido por: 4871,4872
A38: 10.13.00-21.16-041-2025 | B38: NUTRICERES NUEVO 2025-2026 | F38: (SIN RESOLVER -- revisar) | H38: 0 | I38: 1049611.4 | J38: 0 | K38: 1049611.4 | L38: -1049611.4 | M38: — | N38: 1528 | R38: CDP no aparece en el Hacienda de este corte
A39: 10.13.00-22.01-006-2025 | B39: EQUIDE SER | F39: (SIN RESOLVER -- revisar) | H39: 3995143725 | I39: 2665494104 | J39: 0 | K39: 1909748177 | L39: 2085395548 | M39: 0.47801739 | N39: 6 | R39: AMBIGUO -- CDP compartido por: 5304,5307,6076
A40: 10.13.00-22.01-014-2025 | B40: EQUIDE ESAL 015 2025 (PLAN DECENAL) | F40: (SIN RESOLVER -- revisar) | H40: 407239644 | I40: 407239644 | J40: 0 | K40: 302832568 | L40: 104407076 | M40: 0.74362251 | N40: 423 | R40: AMBIGUO -- CDP compartido por: 4874,4875
A42: CONCILIACION RUBRO vs CONTRATOS (solo contratos con match confirmado)
A43: cons_ppt | B43: Proyecto / Rubro | C43: Comprometido rubro (Hacienda) | D43: Suma contratos | E43: Diferencia | F43: Nota
A44: 4959 | B44: Dotación Ley 70/88 Docentes | C44: 18018000 | D44: 18018000 | E44: 0 | F44: OK
A45: 4963 | B45: Fortalecimiento de estrategias para la permanencia escolar svc aseo | C45: 759871200 | D45: 759871200 | E45: 0 | F45: OK
A46: 4967 | B46: Atención a población con necesidades especiales o discapacidades | C46: 379869229 | D46: 379869229 | E46: 0 | F46: OK
A47: 4972 | B47: 020101 VF Fortalecimiento de la pertinencia y la calidad educativa | C47: 2902424207 | D47: 2902424207 | E47: 0 | F47: OK
A48: 4973 | B48: 020101 Fortalecimiento de la pertinencia y la calidad educativa | C48: 20306000 | D48: 20306000 | E48: 0 | F48: OK
A49: 4980 | B49: 020104 Fortalecimiento de la Educación técnica, tecnológica y superior | C49: 849004703 | D49: 849004703 | E49: 0 | F49: OK
A50: 4983 | B50: 020106 Mejoramiento de la cobertura Educativa PAE | C50: 452393559 | D50: 173769267 | E50: 278624292 | F50: Faltan contratos por registrar, o parte del comprometido no tiene CDP-CRP
A51: 4985 | B51: 020106 Mejoramiento de la cobertura Educativa PAE | C51: 27217166386 | D51: 27217166386 | E51: 0 | F51: OK
A52: 4986 | B52: 020106 Mejoramiento de la cobertura Educativa Paquetes PAE | C52: 7320703987 | D52: 3794269403 | E52: 3526434584 | F52: Faltan contratos por registrar, o parte del comprometido no tiene CDP-CRP
A53: 4995 | B53: 020107 Fortalecimiento del programa de Bilinguismo | C53: 1530633596 | D53: 941332078 | E53: 589301518 | F53: Faltan contratos por registrar, o parte del comprometido no tiene CDP-CRP
A54: 4996 | B54: 020108 Fortalecimiento del Bienestar Institucional | C54: 7663802309 | D54: 4222234277 | E54: 3441568032 | F54: Faltan contratos por registrar, o parte del comprometido no tiene CDP-CRP
A55: 6806 | B55: 020106 Mejoramiento de la cobertura Educativa PAE | C55: 2.5451226e+08 | D55: 2.5451226e+08 | E55: 0 | F55: OK
A56: 6848 | B56: 010101 Acompañamiento en la atención a la primera infancia | C56: 1555487503 | D56: 1555487503 | E56: 0 | F56: OK
A58: CALIDAD DEL CRUCE CDP-CRP
A59: OK - match unico por # de CDP | B59: 23
A60: Vigencia futura de otro periodo (normal) | B60: 9
A61: ambiguo | B61: 3
A62: OK - match por CDP + codigo (CDP compartido) | B62: 3
A63: CDP no aparece en el Hacienda de este corte | B63: 1

Sheet NOTAS
A1: Tema | B1: Explicacion
A2: Corte | B2: 15/09/2026 — tomado del nombre del archivo de Hacienda.
A3: Alcance | B3: Vigencia 2026. Es de Educacion todo rubro cuyo cons_ppt esta en la lista maestra RUBROS_EDUCACION (127 cons_ppt confirmados uno por uno sobre el corte 15_09_2026), menos EXCLUSIONES. Se excluye 'Cierre de reservas'. El codigo (02.01/01.01) NO se usa para clasificar: hay rubros hermanos bajo el mismo codigo padre que son de otra Secretaria. El color de cada fila lo pone el sistema solo (MAPA_COLORES); el usuario no tiene que colorear el archivo de Hacienda.
A4: Definitivo | B4: Apropiacion inicial +/- adiciones, reducciones y traslados.
A5: Reservado (CDP) | B5: Certificado de Disponibilidad Presupuestal.
A6: Comprometido (RP) | B6: Registro Presupuestal — respalda contrato u obligacion.
A7: Obligado (OPS) | B7: Orden de Pago — obligacion reconocida y exigible.
A8: Pagado | B8: Giro efectivo. En esta entidad suele coincidir con el obligado del corte.
A9: Sin reservar / comprometer / obligar | B9: Brecha entre una etapa y la siguiente.
A10: Componente | B10: Clasificacion por fuente. Ver hoja EJECUTIVO.
A11: Contratos | B11: Se cargan en seguimiento_manual_educacion.xlsx (hoja CONTRATOS). Cada corrida de GENERAR_INFORME.bat los vuelve a leer: lo que este alli aparece aqui, no hay que copiar nada.
A12: Conciliacion — definitiva | B12: Informe: 219,806,760,754. Seguimiento manual 15/08/2026: 219,422,883,163. Diferencia: 383,877,591.
... A16: Generado | B16: 2026-09-18
